<?xml version="1.0" encoding="utf-8"?>
<CanvasApp xmlns:xsi="http://www.w3.org/2001/XMLSchema-instance">
  <Name>crd30_licensecalculator_1e1f6</Name>
  <AppVersion>2024-01-30T13:43:07Z</AppVersion>
  <Status>Ready</Status>
  <CreatedByClientVersion>3.24014.14.0</CreatedByClientVersion>
  <MinClientVersion>3.24014.14.0</MinClientVersion>
  <Tags>{"primaryDeviceWidth":"1366","primaryDeviceHeight":"768","supportsPortrait":"true","supportsLandscape":"true","primaryFormFactor":"Tablet","showStatusBar":"false","publisherVersion":"3.24014.14","minimumRequiredApiVersion":"2.2.0","hasComponent":"true","hasUnlockedComponent":"false","isUnifiedRootApp":"false","offlineLargeFilesSupport":"false"}</Tags>
  <IsCdsUpgraded>0</IsCdsUpgraded>
  <GalleryItemId xsi:nil="true"></GalleryItemId>
  <BackgroundColor>RGBA(0,176,240,1)</BackgroundColor>
  <DisplayName>License Calculator</DisplayName>
  <Description xsi:nil="true"></Description>
  <CommitMessage xsi:nil="true"></CommitMessage>
  <Publisher xsi:nil="true"></Publisher>
  <AuthorizationReferences>[]</AuthorizationReferences>
  <ConnectionReferences>{}</ConnectionReferences>
  <DatabaseReferences>{}</DatabaseReferences>
  <AppComponents>[]</AppComponents>
  <AppComponentDependencies>[{"appComponentName":"2a52c84637424b1bbab5bd82bb6e33a2","appName":"ae8edea1-bce2-4a7e-957c-5bf65f42e595","appComponentLibraryName":"93fea0ab-8766-4952-8598-45911a542faf","appComponentLibraryVersion":"2024-01-30T13:38:28Z","appComponentLibraryLogicalName":"cr801_componentslibrary_f0cc5","environmentName":"a2501a9b-1447-ee4f-9bdd-bf2a5e95805d"}]</AppComponentDependencies>
  <CanConsumeAppPass>1</CanConsumeAppPass>
  <CanvasAppType>0</CanvasAppType>
  <BypassConsent>0</BypassConsent>
  <AdminControlBypassConsent>0</AdminControlBypassConsent>
  <EmbeddedApp xsi:nil="true"></EmbeddedApp>
  <IntroducedVersion>1.0</IntroducedVersion>
  <CdsDependencies>{"cdsdependencies":[{"logicalname":"cr801_componentslibrary_f0cc5","componenttype":300,"componenttypeplatformname":"CanvasApp"}]}</CdsDependencies>
  <IsCustomizable>1</IsCustomizable>
  <BackgroundImageUri>/CanvasApps/crd30_licensecalculator_1e1f6_BackgroundImageUri</BackgroundImageUri>
  <DocumentUri>/CanvasApps/crd30_licensecalculator_1e1f6_DocumentUri.msapp</DocumentUri>
  <AdditionalUris>
    <AdditionalUri>/CanvasApps/crd30_licensecalculator_1e1f6_AdditionalUris0_identity.json</AdditionalUri>
  </AdditionalUris>
</CanvasApp>