{
  "ComponentAllowCustomization": true,
  "ComponentChangedSinceFileImport": true,
  "ComponentDefinitionInfo": {
    "AllowAccessToGlobals": false,
    "Children": [
      {
        "AllowAccessToGlobals": true,
        "Children": [],
        "ControlPropertyState": [
          "ZIndex",
          "Image",
          "Transparency",
          "ImagePosition",
          "CalculateOriginalDimensions",
          "ImageRotation",
          "FlipHorizontal",
          "FlipVertical",
          "ApplyEXIFOrientation",
          {
            "AFDDataSourceName": "",
            "AutoRuleBindingEnabled": false,
            "AutoRuleBindingString": "\"\"",
            "InvariantPropertyName": "AccessibleLabel",
            "IsLockable": false,
            "NameMapSourceSchema": "?"
          },
          "Tooltip",
          "ContentLanguage",
          "AutoDisableOnSelect",
          "X",
          "Y",
          "Width",
          "Height",
          "Visible",
          "Fill",
          "DisabledFill",
          "PressedFill",
          "HoverFill",
          "BorderColor",
          "RadiusTopLeft",
          "RadiusTopRight",
          "RadiusBottomLeft",
          "RadiusBottomRight",
          "DisabledBorderColor",
          "PressedBorderColor",
          "HoverBorderColor",
          "BorderThickness",
          "FocusedBorderColor",
          "FocusedBorderThickness",
          "BorderStyle",
          "PaddingTop",
          "PaddingRight",
          "PaddingBottom",
          "PaddingLeft",
          "DisplayMode",
          {
            "AFDDataSourceName": "",
            "AutoRuleBindingEnabled": false,
            "AutoRuleBindingString": "-1",
            "InvariantPropertyName": "TabIndex",
            "IsLockable": false,
            "NameMapSourceSchema": "?"
          },
          "OnSelect",
          "minimumWidth",
          "minimumHeight",
          "maximumWidth",
          "maximumHeight"
        ],
        "ControlUniqueId": "5",
        "HasDynamicProperties": false,
        "Index": 0,
        "IsAutoGenerated": false,
        "IsDataControl": false,
        "IsFromScreenLayout": false,
        "IsGroupControl": false,
        "IsLocked": false,
        "LayoutName": "",
        "MetaDataIDKey": "",
        "Name": "menu logo",
        "OptimizeForDevices": "Off",
        "Parent": "menu component",
        "PersistMetaDataIDKey": false,
        "PublishOrderIndex": 93,
        "Rules": [
          {
            "Category": "Data",
            "InvariantScript": "'menu component'.logo",
            "Property": "Image",
            "RuleProviderType": "Unknown"
          },
          {
            "Category": "Data",
            "InvariantScript": "\"logo\"",
            "Property": "AccessibleLabel",
            "RuleProviderType": "User"
          },
          {
            "Category": "Data",
            "InvariantScript": "\"\"",
            "Property": "Tooltip",
            "RuleProviderType": "Unknown"
          },
          {
            "Category": "Data",
            "InvariantScript": "\"\"",
            "Property": "ContentLanguage",
            "RuleProviderType": "Unknown"
          },
          {
            "Category": "Design",
            "InvariantScript": "2",
            "Property": "ZIndex",
            "RuleProviderType": "Unknown"
          },
          {
            "Category": "Design",
            "InvariantScript": "0",
            "Property": "Transparency",
            "RuleProviderType": "Unknown"
          },
          {
            "Category": "Design",
            "InvariantScript": "ImagePosition.Fit",
            "Property": "ImagePosition",
            "RuleProviderType": "Unknown"
          },
          {
            "Category": "Design",
            "InvariantScript": "false",
            "Property": "CalculateOriginalDimensions",
            "RuleProviderType": "Unknown"
          },
          {
            "Category": "Design",
            "InvariantScript": "ImageRotation.None",
            "Property": "ImageRotation",
            "RuleProviderType": "Unknown"
          },
          {
            "Category": "Design",
            "InvariantScript": "false",
            "Property": "FlipHorizontal",
            "RuleProviderType": "Unknown"
          },
          {
            "Category": "Design",
            "InvariantScript": "false",
            "Property": "FlipVertical",
            "RuleProviderType": "Unknown"
          },
          {
            "Category": "Design",
            "InvariantScript": "true",
            "Property": "ApplyEXIFOrientation",
            "RuleProviderType": "Unknown"
          },
          {
            "Category": "Design",
            "InvariantScript": "true",
            "Property": "AutoDisableOnSelect",
            "RuleProviderType": "Unknown"
          },
          {
            "Category": "Design",
            "InvariantScript": "0",
            "Property": "X",
            "RuleProviderType": "Unknown"
          },
          {
            "Category": "Design",
            "InvariantScript": "0",
            "Property": "Y",
            "RuleProviderType": "Unknown"
          },
          {
            "Category": "Design",
            "InvariantScript": "100",
            "Property": "Width",
            "RuleProviderType": "Unknown"
          },
          {
            "Category": "Design",
            "InvariantScript": "100",
            "Property": "Height",
            "RuleProviderType": "Unknown"
          },
          {
            "Category": "Design",
            "InvariantScript": "true",
            "Property": "Visible",
            "RuleProviderType": "Unknown"
          },
          {
            "Category": "Design",
            "InvariantScript": "RGBA(0, 0, 0, 0)",
            "Property": "Fill",
            "RuleProviderType": "Unknown"
          },
          {
            "Category": "Design",
            "InvariantScript": "RGBA(244, 244, 244, 1)",
            "Property": "DisabledFill",
            "RuleProviderType": "Unknown"
          },
          {
            "Category": "Design",
            "InvariantScript": "ColorFade(Self.Fill, -20%)",
            "Property": "PressedFill",
            "RuleProviderType": "Unknown"
          },
          {
            "Category": "Design",
            "InvariantScript": "ColorFade(Self.Fill, 20%)",
            "Property": "HoverFill",
            "RuleProviderType": "Unknown"
          },
          {
            "Category": "Design",
            "InvariantScript": "App.Theme.Colors.Darker40",
            "Property": "BorderColor",
            "RuleProviderType": "Unknown"
          },
          {
            "Category": "Design",
            "InvariantScript": "0",
            "Property": "RadiusTopLeft",
            "RuleProviderType": "Unknown"
          },
          {
            "Category": "Design",
            "InvariantScript": "0",
            "Property": "RadiusTopRight",
            "RuleProviderType": "Unknown"
          },
          {
            "Category": "Design",
            "InvariantScript": "0",
            "Property": "RadiusBottomLeft",
            "RuleProviderType": "Unknown"
          },
          {
            "Category": "Design",
            "InvariantScript": "0",
            "Property": "RadiusBottomRight",
            "RuleProviderType": "Unknown"
          },
          {
            "Category": "Design",
            "InvariantScript": "RGBA(166, 166, 166, 1)",
            "Property": "DisabledBorderColor",
            "RuleProviderType": "Unknown"
          },
          {
            "Category": "Design",
            "InvariantScript": "ColorFade(Self.BorderColor, -20%)",
            "Property": "PressedBorderColor",
            "RuleProviderType": "Unknown"
          },
          {
            "Category": "Design",
            "InvariantScript": "ColorFade(Self.BorderColor, 20%)",
            "Property": "HoverBorderColor",
            "RuleProviderType": "Unknown"
          },
          {
            "Category": "Design",
            "InvariantScript": "0",
            "Property": "BorderThickness",
            "RuleProviderType": "Unknown"
          },
          {
            "Category": "Design",
            "InvariantScript": "Self.BorderColor",
            "Property": "FocusedBorderColor",
            "RuleProviderType": "Unknown"
          },
          {
            "Category": "Design",
            "InvariantScript": "2",
            "Property": "FocusedBorderThickness",
            "RuleProviderType": "Unknown"
          },
          {
            "Category": "Design",
            "InvariantScript": "BorderStyle.Solid",
            "Property": "BorderStyle",
            "RuleProviderType": "Unknown"
          },
          {
            "Category": "Design",
            "InvariantScript": "24",
            "Property": "PaddingTop",
            "RuleProviderType": "Unknown"
          },
          {
            "Category": "Design",
            "InvariantScript": "24",
            "Property": "PaddingRight",
            "RuleProviderType": "Unknown"
          },
          {
            "Category": "Design",
            "InvariantScript": "24",
            "Property": "PaddingBottom",
            "RuleProviderType": "Unknown"
          },
          {
            "Category": "Design",
            "InvariantScript": "24",
            "Property": "PaddingLeft",
            "RuleProviderType": "Unknown"
          },
          {
            "Category": "Design",
            "InvariantScript": "DisplayMode.Edit",
            "Property": "DisplayMode",
            "RuleProviderType": "Unknown"
          },
          {
            "Category": "Design",
            "InvariantScript": "0",
            "Property": "TabIndex",
            "RuleProviderType": "Unknown"
          },
          {
            "Category": "Design",
            "InvariantScript": "1",
            "Property": "minimumWidth",
            "RuleProviderType": "Unknown"
          },
          {
            "Category": "Design",
            "InvariantScript": "1",
            "Property": "minimumHeight",
            "RuleProviderType": "Unknown"
          },
          {
            "Category": "Design",
            "InvariantScript": "1366",
            "Property": "maximumWidth",
            "RuleProviderType": "Unknown"
          },
          {
            "Category": "Design",
            "InvariantScript": "768",
            "Property": "maximumHeight",
            "RuleProviderType": "Unknown"
          },
          {
            "Category": "Behavior",
            "InvariantScript": "false",
            "Property": "OnSelect",
            "RuleProviderType": "Unknown"
          }
        ],
        "StyleName": "defaultImageStyle",
        "Template": {
          "CustomGroupControlTemplateName": "",
          "FirstParty": true,
          "Id": "http://microsoft.com/appmagic/image",
          "IsComponentDefinition": false,
          "IsCustomGroupControlTemplate": false,
          "IsPremiumPcfControl": false,
          "LastModifiedTimestamp": "0",
          "Name": "image",
          "OverridableProperties": {},
          "Version": "2.2.3"
        },
        "Type": "ControlInfo",
        "VariantName": ""
      },
      {
        "AllowAccessToGlobals": true,
        "Children": [
          {
            "AllowAccessToGlobals": true,
            "Children": [],
            "ControlPropertyState": [
              "TemplateFill"
            ],
            "ControlUniqueId": "7",
            "HasDynamicProperties": false,
            "Index": 0,
            "IsAutoGenerated": false,
            "IsDataControl": true,
            "IsFromScreenLayout": false,
            "IsGroupControl": false,
            "IsLocked": false,
            "LayoutName": "",
            "MetaDataIDKey": "",
            "Name": "b448fe5b-7ee2-48c5-9b00-4bcae267e48f",
            "OptimizeForDevices": "Off",
            "Parent": "menu gallery",
            "PersistMetaDataIDKey": false,
            "PublishOrderIndex": 95,
            "Rules": [
              {
                "Category": "Design",
                "InvariantScript": "RGBA(0, 0, 0, 0)",
                "Property": "TemplateFill",
                "RuleProviderType": "Unknown"
              }
            ],
            "StyleName": "",
            "Template": {
              "CustomGroupControlTemplateName": "",
              "FirstParty": true,
              "Id": "http://microsoft.com/appmagic/galleryTemplate",
              "IsComponentDefinition": false,
              "IsCustomGroupControlTemplate": false,
              "IsPremiumPcfControl": false,
              "LastModifiedTimestamp": "0",
              "Name": "galleryTemplate",
              "OverridableProperties": {},
              "Version": "1.0"
            },
            "Type": "ControlInfo",
            "VariantName": ""
          },
          {
            "AllowAccessToGlobals": true,
            "Children": [],
            "ControlPropertyState": [
              "ZIndex",
              {
                "AFDDataSourceName": "",
                "AutoRuleBindingEnabled": false,
                "AutoRuleBindingString": "\"data:image/svg+xml;utf8, \"&EncodeUrl(\"\r\n    \r\n    <svg xmlns='http://www.w3.org/2000/svg' width='10' height='10' fill='\" & \r\n    \r\n    If(\r\n        ThisItem.name = 'menu component'.curentScreen,\r\n        'menu component'.iconColorCurrent,\r\n        'menu component'.iconColor\r\n    )\r\n\r\n    & \"' viewBox='0 0 16 16'>\r\n\r\n    \" & ThisItem.path & \"\r\n\r\n    </svg>\r\n\r\n\")",
                "InvariantPropertyName": "Image",
                "IsLockable": false,
                "NameMapSourceSchema": "?"
              },
              "Transparency",
              "ImagePosition",
              "CalculateOriginalDimensions",
              "ImageRotation",
              "FlipHorizontal",
              "FlipVertical",
              "ApplyEXIFOrientation",
              {
                "AFDDataSourceName": "",
                "AutoRuleBindingEnabled": false,
                "AutoRuleBindingString": "\"\"",
                "InvariantPropertyName": "AccessibleLabel",
                "IsLockable": false,
                "NameMapSourceSchema": "?"
              },
              "Tooltip",
              "ContentLanguage",
              "AutoDisableOnSelect",
              "X",
              "Y",
              "Width",
              "Height",
              "Visible",
              "Fill",
              "DisabledFill",
              "PressedFill",
              "HoverFill",
              "BorderColor",
              "RadiusTopLeft",
              "RadiusTopRight",
              "RadiusBottomLeft",
              "RadiusBottomRight",
              "DisabledBorderColor",
              "PressedBorderColor",
              "HoverBorderColor",
              "BorderThickness",
              "FocusedBorderColor",
              "FocusedBorderThickness",
              "BorderStyle",
              "PaddingTop",
              "PaddingRight",
              "PaddingBottom",
              "PaddingLeft",
              "DisplayMode",
              {
                "AFDDataSourceName": "",
                "AutoRuleBindingEnabled": false,
                "AutoRuleBindingString": "-1",
                "InvariantPropertyName": "TabIndex",
                "IsLockable": false,
                "NameMapSourceSchema": "?"
              },
              "OnSelect",
              "minimumWidth",
              "minimumHeight",
              "maximumWidth",
              "maximumHeight"
            ],
            "ControlUniqueId": "8",
            "HasDynamicProperties": false,
            "Index": 0,
            "IsAutoGenerated": false,
            "IsDataControl": false,
            "IsFromScreenLayout": false,
            "IsGroupControl": false,
            "IsLocked": false,
            "LayoutName": "",
            "MetaDataIDKey": "",
            "Name": "menu icons",
            "OptimizeForDevices": "Off",
            "Parent": "menu gallery",
            "PersistMetaDataIDKey": false,
            "PublishOrderIndex": 96,
            "Rules": [
              {
                "Category": "Data",
                "InvariantScript": "\"data:image/svg+xml;utf8, \"&EncodeUrl(\"\r\n    \r\n    <svg xmlns='http://www.w3.org/2000/svg' width='10' height='10' fill='\" & \r\n    \r\n    If(\r\n        ThisItem.name = 'menu component'.currentScreen,\r\n        'menu component'.iconColorCurrent,\r\n        'menu component'.iconColor\r\n    )\r\n\r\n    & \"' viewBox='0 0 16 16'>\r\n\r\n    \" & ThisItem.path & \"\r\n\r\n    </svg>\r\n\r\n\")",
                "Property": "Image",
                "RuleProviderType": "User"
              },
              {
                "Category": "Data",
                "InvariantScript": "ThisItem.name",
                "Property": "AccessibleLabel",
                "RuleProviderType": "User"
              },
              {
                "Category": "Data",
                "InvariantScript": "ThisItem.name",
                "Property": "Tooltip",
                "RuleProviderType": "Unknown"
              },
              {
                "Category": "Data",
                "InvariantScript": "\"\"",
                "Property": "ContentLanguage",
                "RuleProviderType": "Unknown"
              },
              {
                "Category": "Design",
                "InvariantScript": "1",
                "Property": "ZIndex",
                "RuleProviderType": "Unknown"
              },
              {
                "Category": "Design",
                "InvariantScript": "0",
                "Property": "Transparency",
                "RuleProviderType": "Unknown"
              },
              {
                "Category": "Design",
                "InvariantScript": "ImagePosition.Fit",
                "Property": "ImagePosition",
                "RuleProviderType": "Unknown"
              },
              {
                "Category": "Design",
                "InvariantScript": "false",
                "Property": "CalculateOriginalDimensions",
                "RuleProviderType": "Unknown"
              },
              {
                "Category": "Design",
                "InvariantScript": "ImageRotation.None",
                "Property": "ImageRotation",
                "RuleProviderType": "Unknown"
              },
              {
                "Category": "Design",
                "InvariantScript": "false",
                "Property": "FlipHorizontal",
                "RuleProviderType": "Unknown"
              },
              {
                "Category": "Design",
                "InvariantScript": "false",
                "Property": "FlipVertical",
                "RuleProviderType": "Unknown"
              },
              {
                "Category": "Design",
                "InvariantScript": "true",
                "Property": "ApplyEXIFOrientation",
                "RuleProviderType": "Unknown"
              },
              {
                "Category": "Design",
                "InvariantScript": "true",
                "Property": "AutoDisableOnSelect",
                "RuleProviderType": "Unknown"
              },
              {
                "Category": "Design",
                "InvariantScript": "(Parent.TemplateWidth / 2) - (Self.Width / 2)",
                "Property": "X",
                "RuleProviderType": "Unknown"
              },
              {
                "Category": "Design",
                "InvariantScript": "(Parent.TemplateHeight / 2) - (Self.Height / 2)",
                "Property": "Y",
                "RuleProviderType": "Unknown"
              },
              {
                "Category": "Design",
                "InvariantScript": "20",
                "Property": "Width",
                "RuleProviderType": "Unknown"
              },
              {
                "Category": "Design",
                "InvariantScript": "20",
                "Property": "Height",
                "RuleProviderType": "Unknown"
              },
              {
                "Category": "Design",
                "InvariantScript": "true",
                "Property": "Visible",
                "RuleProviderType": "Unknown"
              },
              {
                "Category": "Design",
                "InvariantScript": "RGBA(0, 0, 0, 0)",
                "Property": "Fill",
                "RuleProviderType": "Unknown"
              },
              {
                "Category": "Design",
                "InvariantScript": "RGBA(244, 244, 244, 1)",
                "Property": "DisabledFill",
                "RuleProviderType": "Unknown"
              },
              {
                "Category": "Design",
                "InvariantScript": "ColorFade(Self.Fill, -20%)",
                "Property": "PressedFill",
                "RuleProviderType": "Unknown"
              },
              {
                "Category": "Design",
                "InvariantScript": "ColorFade(Self.Fill, 20%)",
                "Property": "HoverFill",
                "RuleProviderType": "Unknown"
              },
              {
                "Category": "Design",
                "InvariantScript": "App.Theme.Colors.Darker40",
                "Property": "BorderColor",
                "RuleProviderType": "Unknown"
              },
              {
                "Category": "Design",
                "InvariantScript": "0",
                "Property": "RadiusTopLeft",
                "RuleProviderType": "Unknown"
              },
              {
                "Category": "Design",
                "InvariantScript": "0",
                "Property": "RadiusTopRight",
                "RuleProviderType": "Unknown"
              },
              {
                "Category": "Design",
                "InvariantScript": "0",
                "Property": "RadiusBottomLeft",
                "RuleProviderType": "Unknown"
              },
              {
                "Category": "Design",
                "InvariantScript": "0",
                "Property": "RadiusBottomRight",
                "RuleProviderType": "Unknown"
              },
              {
                "Category": "Design",
                "InvariantScript": "RGBA(166, 166, 166, 1)",
                "Property": "DisabledBorderColor",
                "RuleProviderType": "Unknown"
              },
              {
                "Category": "Design",
                "InvariantScript": "ColorFade(Self.BorderColor, -20%)",
                "Property": "PressedBorderColor",
                "RuleProviderType": "Unknown"
              },
              {
                "Category": "Design",
                "InvariantScript": "ColorFade(Self.BorderColor, 20%)",
                "Property": "HoverBorderColor",
                "RuleProviderType": "Unknown"
              },
              {
                "Category": "Design",
                "InvariantScript": "0",
                "Property": "BorderThickness",
                "RuleProviderType": "Unknown"
              },
              {
                "Category": "Design",
                "InvariantScript": "Self.BorderColor",
                "Property": "FocusedBorderColor",
                "RuleProviderType": "Unknown"
              },
              {
                "Category": "Design",
                "InvariantScript": "2",
                "Property": "FocusedBorderThickness",
                "RuleProviderType": "Unknown"
              },
              {
                "Category": "Design",
                "InvariantScript": "BorderStyle.Solid",
                "Property": "BorderStyle",
                "RuleProviderType": "Unknown"
              },
              {
                "Category": "Design",
                "InvariantScript": "0",
                "Property": "PaddingTop",
                "RuleProviderType": "Unknown"
              },
              {
                "Category": "Design",
                "InvariantScript": "0",
                "Property": "PaddingRight",
                "RuleProviderType": "Unknown"
              },
              {
                "Category": "Design",
                "InvariantScript": "0",
                "Property": "PaddingBottom",
                "RuleProviderType": "Unknown"
              },
              {
                "Category": "Design",
                "InvariantScript": "0",
                "Property": "PaddingLeft",
                "RuleProviderType": "Unknown"
              },
              {
                "Category": "Design",
                "InvariantScript": "DisplayMode.Edit",
                "Property": "DisplayMode",
                "RuleProviderType": "Unknown"
              },
              {
                "Category": "Design",
                "InvariantScript": "0",
                "Property": "TabIndex",
                "RuleProviderType": "Unknown"
              },
              {
                "Category": "Design",
                "InvariantScript": "1",
                "Property": "minimumWidth",
                "RuleProviderType": "Unknown"
              },
              {
                "Category": "Design",
                "InvariantScript": "1",
                "Property": "minimumHeight",
                "RuleProviderType": "Unknown"
              },
              {
                "Category": "Design",
                "InvariantScript": "1366",
                "Property": "maximumWidth",
                "RuleProviderType": "Unknown"
              },
              {
                "Category": "Design",
                "InvariantScript": "768",
                "Property": "maximumHeight",
                "RuleProviderType": "Unknown"
              },
              {
                "Category": "Behavior",
                "InvariantScript": "Navigate(ThisItem.screen)",
                "Property": "OnSelect",
                "RuleProviderType": "Unknown"
              }
            ],
            "StyleName": "defaultImageStyle",
            "Template": {
              "CustomGroupControlTemplateName": "",
              "FirstParty": true,
              "Id": "http://microsoft.com/appmagic/image",
              "IsComponentDefinition": false,
              "IsCustomGroupControlTemplate": false,
              "IsPremiumPcfControl": false,
              "LastModifiedTimestamp": "0",
              "Name": "image",
              "OverridableProperties": {},
              "Version": "2.2.3"
            },
            "Type": "ControlInfo",
            "VariantName": ""
          }
        ],
        "ControlPropertyState": [
          "ZIndex",
          "Items",
          "WrapCount",
          "Selectable",
          "TemplateSize",
          "TemplateMaximumWidth",
          "TemplatePadding",
          "MaxTemplateSize",
          "Layout",
          "Transition",
          "ShowNavigation",
          "NavigationStep",
          "ShowScrollbar",
          "SelectionTracksMove",
          "Reset",
          "AutoHeight",
          "DelayItemLoading",
          "LoadingSpinner",
          "LoadingSpinnerColor",
          {
            "AFDDataSourceName": "",
            "AutoRuleBindingEnabled": false,
            "AutoRuleBindingString": "\"\"",
            "InvariantPropertyName": "AccessibleLabel",
            "IsLockable": false,
            "NameMapSourceSchema": "?"
          },
          "ContentLanguage",
          "DisplayMode",
          "BorderColor",
          "DisabledBorderColor",
          "PressedBorderColor",
          "HoverBorderColor",
          "BorderThickness",
          "BorderStyle",
          "FocusedBorderColor",
          "FocusedBorderThickness",
          "Fill",
          "DisabledFill",
          "PressedFill",
          "HoverFill",
          "X",
          "Y",
          "Width",
          "Height",
          "Visible",
          {
            "AFDDataSourceName": "",
            "AutoRuleBindingEnabled": false,
            "AutoRuleBindingString": "-1",
            "InvariantPropertyName": "TabIndex",
            "IsLockable": false,
            "NameMapSourceSchema": "?"
          },
          "minimumWidth",
          "minimumHeight",
          "maximumWidth",
          "maximumHeight",
          "#CopilotOverlayLabel",
          "#CopilotOverlayVisible"
        ],
        "ControlUniqueId": "6",
        "HasDynamicProperties": false,
        "Index": 0,
        "IsAutoGenerated": false,
        "IsDataControl": false,
        "IsFromScreenLayout": false,
        "IsGroupControl": false,
        "IsLocked": false,
        "LayoutName": "",
        "MetaDataIDKey": "",
        "Name": "menu gallery",
        "OptimizeForDevices": "Off",
        "Parent": "menu component",
        "PersistMetaDataIDKey": false,
        "PublishOrderIndex": 94,
        "Rules": [
          {
            "Category": "Data",
            "InvariantScript": "'menu component'.menuIcons",
            "Property": "Items",
            "RuleProviderType": "Unknown"
          },
          {
            "Category": "Data",
            "InvariantScript": "1",
            "Property": "WrapCount",
            "RuleProviderType": "Unknown"
          },
          {
            "Category": "Data",
            "InvariantScript": "true",
            "Property": "Selectable",
            "RuleProviderType": "Unknown"
          },
          {
            "Category": "Data",
            "InvariantScript": "false",
            "Property": "Reset",
            "RuleProviderType": "Unknown"
          },
          {
            "Category": "Data",
            "InvariantScript": "\"Menu options\"",
            "Property": "AccessibleLabel",
            "RuleProviderType": "User"
          },
          {
            "Category": "Data",
            "InvariantScript": "\"\"",
            "Property": "ContentLanguage",
            "RuleProviderType": "Unknown"
          },
          {
            "Category": "Design",
            "InvariantScript": "1",
            "Property": "ZIndex",
            "RuleProviderType": "Unknown"
          },
          {
            "Category": "Design",
            "InvariantScript": "80",
            "Property": "TemplateSize",
            "RuleProviderType": "Unknown"
          },
          {
            "Category": "Design",
            "InvariantScript": "0",
            "Property": "TemplateMaximumWidth",
            "RuleProviderType": "Unknown"
          },
          {
            "Category": "Design",
            "InvariantScript": "0",
            "Property": "TemplatePadding",
            "RuleProviderType": "Unknown"
          },
          {
            "Category": "Design",
            "InvariantScript": "5000",
            "Property": "MaxTemplateSize",
            "RuleProviderType": "Unknown"
          },
          {
            "Category": "Design",
            "InvariantScript": "Layout.Vertical",
            "Property": "Layout",
            "RuleProviderType": "Unknown"
          },
          {
            "Category": "Design",
            "InvariantScript": "Transition.Push",
            "Property": "Transition",
            "RuleProviderType": "Unknown"
          },
          {
            "Category": "Design",
            "InvariantScript": "false",
            "Property": "ShowNavigation",
            "RuleProviderType": "Unknown"
          },
          {
            "Category": "Design",
            "InvariantScript": "1",
            "Property": "NavigationStep",
            "RuleProviderType": "Unknown"
          },
          {
            "Category": "Design",
            "InvariantScript": "true",
            "Property": "ShowScrollbar",
            "RuleProviderType": "Unknown"
          },
          {
            "Category": "Design",
            "InvariantScript": "false",
            "Property": "SelectionTracksMove",
            "RuleProviderType": "Unknown"
          },
          {
            "Category": "Design",
            "InvariantScript": "false",
            "Property": "AutoHeight",
            "RuleProviderType": "Unknown"
          },
          {
            "Category": "Design",
            "InvariantScript": "true",
            "Property": "DelayItemLoading",
            "RuleProviderType": "Unknown"
          },
          {
            "Category": "Design",
            "InvariantScript": "LoadingSpinner.Data",
            "Property": "LoadingSpinner",
            "RuleProviderType": "Unknown"
          },
          {
            "Category": "Design",
            "InvariantScript": "Self.BorderColor",
            "Property": "LoadingSpinnerColor",
            "RuleProviderType": "Unknown"
          },
          {
            "Category": "Design",
            "InvariantScript": "DisplayMode.Edit",
            "Property": "DisplayMode",
            "RuleProviderType": "Unknown"
          },
          {
            "Category": "Design",
            "InvariantScript": "App.Theme.Colors.Darker40",
            "Property": "BorderColor",
            "RuleProviderType": "Unknown"
          },
          {
            "Category": "Design",
            "InvariantScript": "Self.BorderColor",
            "Property": "DisabledBorderColor",
            "RuleProviderType": "Unknown"
          },
          {
            "Category": "Design",
            "InvariantScript": "Self.BorderColor",
            "Property": "PressedBorderColor",
            "RuleProviderType": "Unknown"
          },
          {
            "Category": "Design",
            "InvariantScript": "Self.BorderColor",
            "Property": "HoverBorderColor",
            "RuleProviderType": "Unknown"
          },
          {
            "Category": "Design",
            "InvariantScript": "0",
            "Property": "BorderThickness",
            "RuleProviderType": "Unknown"
          },
          {
            "Category": "Design",
            "InvariantScript": "BorderStyle.Solid",
            "Property": "BorderStyle",
            "RuleProviderType": "Unknown"
          },
          {
            "Category": "Design",
            "InvariantScript": "Self.BorderColor",
            "Property": "FocusedBorderColor",
            "RuleProviderType": "Unknown"
          },
          {
            "Category": "Design",
            "InvariantScript": "4",
            "Property": "FocusedBorderThickness",
            "RuleProviderType": "Unknown"
          },
          {
            "Category": "Design",
            "InvariantScript": "RGBA(0, 0, 0, 0)",
            "Property": "Fill",
            "RuleProviderType": "Unknown"
          },
          {
            "Category": "Design",
            "InvariantScript": "Self.Fill",
            "Property": "DisabledFill",
            "RuleProviderType": "Unknown"
          },
          {
            "Category": "Design",
            "InvariantScript": "Self.Fill",
            "Property": "PressedFill",
            "RuleProviderType": "Unknown"
          },
          {
            "Category": "Design",
            "InvariantScript": "Self.Fill",
            "Property": "HoverFill",
            "RuleProviderType": "Unknown"
          },
          {
            "Category": "Design",
            "InvariantScript": "0",
            "Property": "X",
            "RuleProviderType": "Unknown"
          },
          {
            "Category": "Design",
            "InvariantScript": "'menu logo'.Y + 'menu logo'.Height",
            "Property": "Y",
            "RuleProviderType": "Unknown"
          },
          {
            "Category": "Design",
            "InvariantScript": "Parent.Width",
            "Property": "Width",
            "RuleProviderType": "Unknown"
          },
          {
            "Category": "Design",
            "InvariantScript": "Parent.Height - Self.Y",
            "Property": "Height",
            "RuleProviderType": "Unknown"
          },
          {
            "Category": "Design",
            "InvariantScript": "true",
            "Property": "Visible",
            "RuleProviderType": "Unknown"
          },
          {
            "Category": "Design",
            "InvariantScript": "0",
            "Property": "TabIndex",
            "RuleProviderType": "Unknown"
          },
          {
            "Category": "Design",
            "InvariantScript": "20",
            "Property": "minimumWidth",
            "RuleProviderType": "Unknown"
          },
          {
            "Category": "Design",
            "InvariantScript": "20",
            "Property": "minimumHeight",
            "RuleProviderType": "Unknown"
          },
          {
            "Category": "Design",
            "InvariantScript": "1366",
            "Property": "maximumWidth",
            "RuleProviderType": "Unknown"
          },
          {
            "Category": "Design",
            "InvariantScript": "768",
            "Property": "maximumHeight",
            "RuleProviderType": "Unknown"
          },
          {
            "Category": "Design",
            "InvariantScript": "\"Filtered\"",
            "Property": "#CopilotOverlayLabel",
            "RuleProviderType": "Unknown"
          },
          {
            "Category": "Design",
            "InvariantScript": "false",
            "Property": "#CopilotOverlayVisible",
            "RuleProviderType": "Unknown"
          }
        ],
        "StyleName": "defaultGalleryStyle",
        "Template": {
          "CustomGroupControlTemplateName": "",
          "FirstParty": true,
          "Id": "http://microsoft.com/appmagic/gallery",
          "IsComponentDefinition": false,
          "IsCustomGroupControlTemplate": false,
          "IsPremiumPcfControl": false,
          "LastModifiedTimestamp": "0",
          "Name": "gallery",
          "OverridableProperties": {},
          "Version": "2.15.0"
        },
        "Type": "ControlInfo",
        "VariantName": "BrowseLayout_Vertical_OneTextOneImageVariant_ver5.0"
      }
    ],
    "ControlPropertyState": [
      "Fill",
      "Height",
      "Width",
      "X",
      "Y",
      "Visible",
      "ChildTabPriority",
      "EnableChildFocus",
      "ContentLanguage",
      "ZIndex",
      "parentHeight",
      {
        "AFDDataSourceName": "",
        "AutoRuleBindingEnabled": false,
        "AutoRuleBindingString": "Table(\r\n    {\r\n        id: 1,\r\n        name: \"Instructions\",\r\n        path: \"<path d='M6.428 1.151C6.708.591 7.213 0 8 0s1.292.592 1.572 1.151C9.861 1.73 10 2.431 10 3v3.691l5.17 2.585a1.5 1.5 0 0 1 .83 1.342V12a.5.5 0 0 1-.582.493l-5.507-.918-.375 2.253 1.318 1.318A.5.5 0 0 1 10.5 16h-5a.5.5 0 0 1-.354-.854l1.319-1.318-.376-2.253-5.507.918A.5.5 0 0 1 0 12v-1.382a1.5 1.5 0 0 1 .83-1.342L6 6.691V3c0-.568.14-1.271.428-1.849m.894.448C7.111 2.02 7 2.569 7 3v4a.5.5 0 0 1-.276.447l-5.448 2.724a.5.5 0 0 0-.276.447v.792l5.418-.903a.5.5 0 0 1 .575.41l.5 3a.5.5 0 0 1-.14.437L6.708 15h2.586l-.647-.646a.5.5 0 0 1-.14-.436l.5-3a.5.5 0 0 1 .576-.411L15 11.41v-.792a.5.5 0 0 0-.276-.447L9.276 7.447A.5.5 0 0 1 9 7V3c0-.432-.11-.979-.322-1.401C8.458 1.159 8.213 1 8 1s-.458.158-.678.599'/>\",\r\n        screen: Instructio\r\n    },\r\n    {\r\n        id: 2,\r\n        name: \"Settings\",\r\n        path: \"<path d='M6.428 1.151C6.708.591 7.213 0 8 0s1.292.592 1.572 1.151C9.861 1.73 10 2.431 10 3v3.691l5.17 2.585a1.5 1.5 0 0 1 .83 1.342V12a.5.5 0 0 1-.582.493l-5.507-.918-.375 2.253 1.318 1.318A.5.5 0 0 1 10.5 16h-5a.5.5 0 0 1-.354-.854l1.319-1.318-.376-2.253-5.507.918A.5.5 0 0 1 0 12v-1.382a1.5 1.5 0 0 1 .83-1.342L6 6.691V3c0-.568.14-1.271.428-1.849m.894.448C7.111 2.02 7 2.569 7 3v4a.5.5 0 0 1-.276.447l-5.448 2.724a.5.5 0 0 0-.276.447v.792l5.418-.903a.5.5 0 0 1 .575.41l.5 3a.5.5 0 0 1-.14.437L6.708 15h2.586l-.647-.646a.5.5 0 0 1-.14-.436l.5-3a.5.5 0 0 1 .576-.411L15 11.41v-.792a.5.5 0 0 0-.276-.447L9.276 7.447A.5.5 0 0 1 9 7V3c0-.432-.11-.979-.322-1.401C8.458 1.159 8.213 1 8 1s-.458.158-.678.599'/>\",\r\n        screen: App.ActiveScreen\r\n    },\r\n    {\r\n        id: 3,\r\n        name: \"Analytics\",\r\n        path: \"<path d='M6.428 1.151C6.708.591 7.213 0 8 0s1.292.592 1.572 1.151C9.861 1.73 10 2.431 10 3v3.691l5.17 2.585a1.5 1.5 0 0 1 .83 1.342V12a.5.5 0 0 1-.582.493l-5.507-.918-.375 2.253 1.318 1.318A.5.5 0 0 1 10.5 16h-5a.5.5 0 0 1-.354-.854l1.319-1.318-.376-2.253-5.507.918A.5.5 0 0 1 0 12v-1.382a1.5 1.5 0 0 1 .83-1.342L6 6.691V3c0-.568.14-1.271.428-1.849m.894.448C7.111 2.02 7 2.569 7 3v4a.5.5 0 0 1-.276.447l-5.448 2.724a.5.5 0 0 0-.276.447v.792l5.418-.903a.5.5 0 0 1 .575.41l.5 3a.5.5 0 0 1-.14.437L6.708 15h2.586l-.647-.646a.5.5 0 0 1-.14-.436l.5-3a.5.5 0 0 1 .576-.411L15 11.41v-.792a.5.5 0 0 0-.276-.447L9.276 7.447A.5.5 0 0 1 9 7V3c0-.432-.11-.979-.322-1.401C8.458 1.159 8.213 1 8 1s-.458.158-.678.599'/>\",\r\n        screen: App.ActiveScreen\r\n    },\r\n    {\r\n        id: 4,\r\n        name: \"About\",\r\n        path: \"<path d='M6.428 1.151C6.708.591 7.213 0 8 0s1.292.592 1.572 1.151C9.861 1.73 10 2.431 10 3v3.691l5.17 2.585a1.5 1.5 0 0 1 .83 1.342V12a.5.5 0 0 1-.582.493l-5.507-.918-.375 2.253 1.318 1.318A.5.5 0 0 1 10.5 16h-5a.5.5 0 0 1-.354-.854l1.319-1.318-.376-2.253-5.507.918A.5.5 0 0 1 0 12v-1.382a1.5 1.5 0 0 1 .83-1.342L6 6.691V3c0-.568.14-1.271.428-1.849m.894.448C7.111 2.02 7 2.569 7 3v4a.5.5 0 0 1-.276.447l-5.448 2.724a.5.5 0 0 0-.276.447v.792l5.418-.903a.5.5 0 0 1 .575.41l.5 3a.5.5 0 0 1-.14.437L6.708 15h2.586l-.647-.646a.5.5 0 0 1-.14-.436l.5-3a.5.5 0 0 1 .576-.411L15 11.41v-.792a.5.5 0 0 0-.276-.447L9.276 7.447A.5.5 0 0 1 9 7V3c0-.432-.11-.979-.322-1.401C8.458 1.159 8.213 1 8 1s-.458.158-.678.599'/>\",\r\n        screen: App.ActiveScreen\r\n    }\r\n)",
        "InvariantPropertyName": "menuIcons",
        "IsLockable": false,
        "NameMapSourceSchema": "?"
      },
      {
        "AFDDataSourceName": "",
        "AutoRuleBindingEnabled": false,
        "AutoRuleBindingString": "\"Text\"",
        "InvariantPropertyName": "iconColor",
        "IsLockable": false,
        "NameMapSourceSchema": "?"
      },
      {
        "AFDDataSourceName": "",
        "AutoRuleBindingEnabled": false,
        "AutoRuleBindingString": "\"Text\"",
        "InvariantPropertyName": "logo",
        "IsLockable": false,
        "NameMapSourceSchema": "?"
      },
      {
        "AFDDataSourceName": "",
        "AutoRuleBindingEnabled": false,
        "AutoRuleBindingString": "\"Text\"",
        "InvariantPropertyName": "currentScreen",
        "IsLockable": false,
        "NameMapSourceSchema": "?"
      },
      {
        "AFDDataSourceName": "",
        "AutoRuleBindingEnabled": false,
        "AutoRuleBindingString": "\"Text\"",
        "InvariantPropertyName": "iconColorCurrent",
        "IsLockable": false,
        "NameMapSourceSchema": "?"
      }
    ],
    "LastModifiedTimestamp": "638762695597747879",
    "Name": "menu component",
    "Rules": [
      {
        "Category": "Data",
        "InvariantScript": "\"\"",
        "Property": "ContentLanguage",
        "RuleProviderType": "System"
      },
      {
        "Category": "Data",
        "InvariantScript": "100",
        "Property": "parentHeight",
        "RuleProviderType": "System"
      },
      {
        "Category": "Data",
        "InvariantScript": "Table(\r\n    {\r\n        id: 1,\r\n        name: \"Instructions\",\r\n        path: \"<path d='M6.428 1.151C6.708.591 7.213 0 8 0s1.292.592 1.572 1.151C9.861 1.73 10 2.431 10 3v3.691l5.17 2.585a1.5 1.5 0 0 1 .83 1.342V12a.5.5 0 0 1-.582.493l-5.507-.918-.375 2.253 1.318 1.318A.5.5 0 0 1 10.5 16h-5a.5.5 0 0 1-.354-.854l1.319-1.318-.376-2.253-5.507.918A.5.5 0 0 1 0 12v-1.382a1.5 1.5 0 0 1 .83-1.342L6 6.691V3c0-.568.14-1.271.428-1.849m.894.448C7.111 2.02 7 2.569 7 3v4a.5.5 0 0 1-.276.447l-5.448 2.724a.5.5 0 0 0-.276.447v.792l5.418-.903a.5.5 0 0 1 .575.41l.5 3a.5.5 0 0 1-.14.437L6.708 15h2.586l-.647-.646a.5.5 0 0 1-.14-.436l.5-3a.5.5 0 0 1 .576-.411L15 11.41v-.792a.5.5 0 0 0-.276-.447L9.276 7.447A.5.5 0 0 1 9 7V3c0-.432-.11-.979-.322-1.401C8.458 1.159 8.213 1 8 1s-.458.158-.678.599'/>\",\r\n        screen: 'Prompt refinement'\r\n    },\r\n    {\r\n        id: 2,\r\n        name: \"Settings\",\r\n        path: \"<path d='M6.428 1.151C6.708.591 7.213 0 8 0s1.292.592 1.572 1.151C9.861 1.73 10 2.431 10 3v3.691l5.17 2.585a1.5 1.5 0 0 1 .83 1.342V12a.5.5 0 0 1-.582.493l-5.507-.918-.375 2.253 1.318 1.318A.5.5 0 0 1 10.5 16h-5a.5.5 0 0 1-.354-.854l1.319-1.318-.376-2.253-5.507.918A.5.5 0 0 1 0 12v-1.382a1.5 1.5 0 0 1 .83-1.342L6 6.691V3c0-.568.14-1.271.428-1.849m.894.448C7.111 2.02 7 2.569 7 3v4a.5.5 0 0 1-.276.447l-5.448 2.724a.5.5 0 0 0-.276.447v.792l5.418-.903a.5.5 0 0 1 .575.41l.5 3a.5.5 0 0 1-.14.437L6.708 15h2.586l-.647-.646a.5.5 0 0 1-.14-.436l.5-3a.5.5 0 0 1 .576-.411L15 11.41v-.792a.5.5 0 0 0-.276-.447L9.276 7.447A.5.5 0 0 1 9 7V3c0-.432-.11-.979-.322-1.401C8.458 1.159 8.213 1 8 1s-.458.158-.678.599'/>\",\r\n        screen: 'Prompt refinement'\r\n    },\r\n    {\r\n        id: 3,\r\n        name: \"Analytics\",\r\n        path: \"<path d='M6.428 1.151C6.708.591 7.213 0 8 0s1.292.592 1.572 1.151C9.861 1.73 10 2.431 10 3v3.691l5.17 2.585a1.5 1.5 0 0 1 .83 1.342V12a.5.5 0 0 1-.582.493l-5.507-.918-.375 2.253 1.318 1.318A.5.5 0 0 1 10.5 16h-5a.5.5 0 0 1-.354-.854l1.319-1.318-.376-2.253-5.507.918A.5.5 0 0 1 0 12v-1.382a1.5 1.5 0 0 1 .83-1.342L6 6.691V3c0-.568.14-1.271.428-1.849m.894.448C7.111 2.02 7 2.569 7 3v4a.5.5 0 0 1-.276.447l-5.448 2.724a.5.5 0 0 0-.276.447v.792l5.418-.903a.5.5 0 0 1 .575.41l.5 3a.5.5 0 0 1-.14.437L6.708 15h2.586l-.647-.646a.5.5 0 0 1-.14-.436l.5-3a.5.5 0 0 1 .576-.411L15 11.41v-.792a.5.5 0 0 0-.276-.447L9.276 7.447A.5.5 0 0 1 9 7V3c0-.432-.11-.979-.322-1.401C8.458 1.159 8.213 1 8 1s-.458.158-.678.599'/>\",\r\n        screen: 'Prompt refinement'\r\n    },\r\n    {\r\n        id: 4,\r\n        name: \"About\",\r\n        path: \"<path d='M6.428 1.151C6.708.591 7.213 0 8 0s1.292.592 1.572 1.151C9.861 1.73 10 2.431 10 3v3.691l5.17 2.585a1.5 1.5 0 0 1 .83 1.342V12a.5.5 0 0 1-.582.493l-5.507-.918-.375 2.253 1.318 1.318A.5.5 0 0 1 10.5 16h-5a.5.5 0 0 1-.354-.854l1.319-1.318-.376-2.253-5.507.918A.5.5 0 0 1 0 12v-1.382a1.5 1.5 0 0 1 .83-1.342L6 6.691V3c0-.568.14-1.271.428-1.849m.894.448C7.111 2.02 7 2.569 7 3v4a.5.5 0 0 1-.276.447l-5.448 2.724a.5.5 0 0 0-.276.447v.792l5.418-.903a.5.5 0 0 1 .575.41l.5 3a.5.5 0 0 1-.14.437L6.708 15h2.586l-.647-.646a.5.5 0 0 1-.14-.436l.5-3a.5.5 0 0 1 .576-.411L15 11.41v-.792a.5.5 0 0 0-.276-.447L9.276 7.447A.5.5 0 0 1 9 7V3c0-.432-.11-.979-.322-1.401C8.458 1.159 8.213 1 8 1s-.458.158-.678.599'/>\",\r\n        screen: 'Prompt refinement'\r\n    }\r\n)",
        "Property": "menuIcons",
        "RuleProviderType": "System"
      },
      {
        "Category": "Data",
        "InvariantScript": "\"#354765\"",
        "Property": "iconColor",
        "RuleProviderType": "System"
      },
      {
        "Category": "Data",
        "InvariantScript": "logo",
        "Property": "logo",
        "RuleProviderType": "System"
      },
      {
        "Category": "Data",
        "InvariantScript": "\"Instructions\"",
        "Property": "currentScreen",
        "RuleProviderType": "System"
      },
      {
        "Category": "Data",
        "InvariantScript": "\"#6D62E4\"",
        "Property": "iconColorCurrent",
        "RuleProviderType": "System"
      },
      {
        "Category": "Design",
        "InvariantScript": "RGBA(0, 0, 0, 0)",
        "Property": "Fill",
        "RuleProviderType": "System"
      },
      {
        "Category": "Design",
        "InvariantScript": "500 //Component1.parentHeight",
        "Property": "Height",
        "RuleProviderType": "System"
      },
      {
        "Category": "Design",
        "InvariantScript": "100",
        "Property": "Width",
        "RuleProviderType": "Unknown"
      },
      {
        "Category": "Design",
        "InvariantScript": "0",
        "Property": "X",
        "RuleProviderType": "Unknown"
      },
      {
        "Category": "Design",
        "InvariantScript": "0",
        "Property": "Y",
        "RuleProviderType": "Unknown"
      },
      {
        "Category": "Design",
        "InvariantScript": "true",
        "Property": "Visible",
        "RuleProviderType": "System"
      },
      {
        "Category": "Design",
        "InvariantScript": "true",
        "Property": "ChildTabPriority",
        "RuleProviderType": "System"
      },
      {
        "Category": "Design",
        "InvariantScript": "true",
        "Property": "EnableChildFocus",
        "RuleProviderType": "System"
      },
      {
        "Category": "Design",
        "InvariantScript": "1",
        "Property": "ZIndex",
        "RuleProviderType": "Unknown"
      }
    ]
  },
  "ComponentManifest": {
    "AllowAccessToGlobals": false,
    "AllowCustomization": true,
    "Description": "",
    "Name": "menu component",
    "TemplateGuid": "b6e286b74ab5404c9b80877af1a44005"
  },
  "ComponentType": "CanvasComponent",
  "CustomGroupControlTemplateName": "",
  "CustomProperties": [
    {
      "Category": 0,
      "DisplayName": "parentHeight",
      "Hidden": false,
      "Name": "parentHeight",
      "PropertyDataTypeKey": "Number",
      "Tooltip": "A custom property",
      "Type": "{\"Version\":\"1.345\",\"Type\":{\"Name\":\"Root\",\"Kind\":\"Number\",\"EnumString\":\"\",\"Type\":[]}}"
    },
    {
      "Category": 0,
      "DisplayName": "menuIcons",
      "Hidden": false,
      "Name": "menuIcons",
      "PropertyDataTypeKey": "Table",
      "Tooltip": "A custom property",
      "Type": "{\"Version\":\"1.345\",\"Type\":{\"Name\":\"Root\",\"Kind\":\"Table\",\"EnumString\":\"\",\"Type\":[{\"Name\":\"id\",\"Kind\":\"Number\",\"EnumString\":\"\",\"Type\":[]},{\"Name\":\"name\",\"Kind\":\"String\",\"EnumString\":\"\",\"Type\":[]},{\"Name\":\"path\",\"Kind\":\"String\",\"EnumString\":\"\",\"Type\":[]},{\"Name\":\"screen\",\"Kind\":\"_LimPrimitive\",\"EnumString\":\"\",\"Template\":{\"TemplateName\":\"screen\",\"IsMetaLoc\":false,\"Intangible\":false,\"ExpandoType\":{\"Version\":\"1.345\",\"Type\":{\"Name\":\"Root\",\"Kind\":\"Record\",\"EnumString\":\"\",\"Type\":[{\"Name\":\"BackgroundImage\",\"Kind\":\"Image\",\"EnumString\":\"\",\"Type\":[]},{\"Name\":\"ContentLanguage\",\"Kind\":\"String\",\"EnumString\":\"\",\"Type\":[]},{\"Name\":\"Fill\",\"Kind\":\"Color\",\"EnumString\":\"\",\"Type\":[]},{\"Name\":\"Height\",\"Kind\":\"Number\",\"EnumString\":\"\",\"Type\":[]},{\"Name\":\"ImagePosition\",\"Kind\":\"Enum\",\"EnumString\":\"%s[Center:\\\"center\\\", Fill:\\\"fill\\\", Fit:\\\"fit\\\", Stretch:\\\"stretch\\\", Tile:\\\"tile\\\"]\",\"Type\":[{\"Name\":\"Center\",\"Kind\":\"String\",\"EnumString\":\"\",\"Type\":[]},{\"Name\":\"Fill\",\"Kind\":\"String\",\"EnumString\":\"\",\"Type\":[]},{\"Name\":\"Fit\",\"Kind\":\"String\",\"EnumString\":\"\",\"Type\":[]},{\"Name\":\"Stretch\",\"Kind\":\"String\",\"EnumString\":\"\",\"Type\":[]},{\"Name\":\"Tile\",\"Kind\":\"String\",\"EnumString\":\"\",\"Type\":[]}]},{\"Name\":\"LoadingSpinner\",\"Kind\":\"Enum\",\"EnumString\":\"%n[Controls:0, Data:1, None:2]\",\"Type\":[{\"Name\":\"Controls\",\"Kind\":\"Number\",\"EnumString\":\"\",\"Type\":[]},{\"Name\":\"Data\",\"Kind\":\"Number\",\"EnumString\":\"\",\"Type\":[]},{\"Name\":\"None\",\"Kind\":\"Number\",\"EnumString\":\"\",\"Type\":[]}]},{\"Name\":\"LoadingSpinnerColor\",\"Kind\":\"Color\",\"EnumString\":\"\",\"Type\":[]},{\"Name\":\"Name\",\"Kind\":\"String\",\"EnumString\":\"\",\"Type\":[]},{\"Name\":\"Orientation\",\"Kind\":\"String\",\"EnumString\":\"\",\"Type\":[]},{\"Name\":\"Printing\",\"Kind\":\"Boolean\",\"EnumString\":\"\",\"Type\":[]},{\"Name\":\"Size\",\"Kind\":\"Number\",\"EnumString\":\"\",\"Type\":[]},{\"Name\":\"Width\",\"Kind\":\"Number\",\"EnumString\":\"\",\"Type\":[]}]}},\"Properties\":[{\"Name\":\"Fill\",\"InvariantType\":{\"Version\":\"1.345\",\"Type\":{\"Name\":\"Root\",\"Kind\":\"Color\",\"EnumString\":\"\",\"Type\":[]}},\"PropertyRuleCategory\":\"Design\",\"PropertyDisplayName\":\"Fill\"},{\"Name\":\"BackgroundImage\",\"InvariantType\":{\"Version\":\"1.345\",\"Type\":{\"Name\":\"Root\",\"Kind\":\"Image\",\"EnumString\":\"\",\"Type\":[]}},\"PropertyRuleCategory\":\"Data\",\"PropertyDisplayName\":\"Background image\"},{\"Name\":\"ImagePosition\",\"InvariantType\":{\"Version\":\"1.345\",\"Type\":{\"Name\":\"Root\",\"Kind\":\"Enum\",\"EnumString\":\"%s[Center:\\\"center\\\", Fill:\\\"fill\\\", Fit:\\\"fit\\\", Stretch:\\\"stretch\\\", Tile:\\\"tile\\\"]\",\"Type\":[{\"Name\":\"Center\",\"Kind\":\"String\",\"EnumString\":\"\",\"Type\":[]},{\"Name\":\"Fill\",\"Kind\":\"String\",\"EnumString\":\"\",\"Type\":[]},{\"Name\":\"Fit\",\"Kind\":\"String\",\"EnumString\":\"\",\"Type\":[]},{\"Name\":\"Stretch\",\"Kind\":\"String\",\"EnumString\":\"\",\"Type\":[]},{\"Name\":\"Tile\",\"Kind\":\"String\",\"EnumString\":\"\",\"Type\":[]}]}},\"PropertyRuleCategory\":\"Design\",\"PropertyDisplayName\":\"Image position\"},{\"Name\":\"Height\",\"InvariantType\":{\"Version\":\"1.345\",\"Type\":{\"Name\":\"Root\",\"Kind\":\"Number\",\"EnumString\":\"\",\"Type\":[]}},\"PropertyRuleCategory\":\"Design\",\"PropertyDisplayName\":\"Height\"},{\"Name\":\"Width\",\"InvariantType\":{\"Version\":\"1.345\",\"Type\":{\"Name\":\"Root\",\"Kind\":\"Number\",\"EnumString\":\"\",\"Type\":[]}},\"PropertyRuleCategory\":\"Design\",\"PropertyDisplayName\":\"Width\"},{\"Name\":\"Size\",\"InvariantType\":{\"Version\":\"1.345\",\"Type\":{\"Name\":\"Root\",\"Kind\":\"Number\",\"EnumString\":\"\",\"Type\":[]}},\"PropertyRuleCategory\":\"Design\",\"PropertyDisplayName\":\"Size\"},{\"Name\":\"Orientation\",\"InvariantType\":{\"Version\":\"1.345\",\"Type\":{\"Name\":\"Root\",\"Kind\":\"String\",\"EnumString\":\"\",\"Type\":[]}},\"PropertyRuleCategory\":\"Design\",\"PropertyDisplayName\":\"Orientation\"},{\"Name\":\"LoadingSpinner\",\"InvariantType\":{\"Version\":\"1.345\",\"Type\":{\"Name\":\"Root\",\"Kind\":\"Enum\",\"EnumString\":\"%n[Controls:0, Data:1, None:2]\",\"Type\":[{\"Name\":\"Controls\",\"Kind\":\"Number\",\"EnumString\":\"\",\"Type\":[]},{\"Name\":\"Data\",\"Kind\":\"Number\",\"EnumString\":\"\",\"Type\":[]},{\"Name\":\"None\",\"Kind\":\"Number\",\"EnumString\":\"\",\"Type\":[]}]}},\"PropertyRuleCategory\":\"Design\",\"PropertyDisplayName\":\"Loading spinner\"},{\"Name\":\"LoadingSpinnerColor\",\"InvariantType\":{\"Version\":\"1.345\",\"Type\":{\"Name\":\"Root\",\"Kind\":\"Color\",\"EnumString\":\"\",\"Type\":[]}},\"PropertyRuleCategory\":\"Design\",\"PropertyDisplayName\":\"Loading spinner color\"},{\"Name\":\"Name\",\"InvariantType\":{\"Version\":\"1.345\",\"Type\":{\"Name\":\"Root\",\"Kind\":\"String\",\"EnumString\":\"\",\"Type\":[]}},\"PropertyRuleCategory\":\"Design\",\"PropertyDisplayName\":\"Name\"},{\"Name\":\"Printing\",\"InvariantType\":{\"Version\":\"1.345\",\"Type\":{\"Name\":\"Root\",\"Kind\":\"Boolean\",\"EnumString\":\"\",\"Type\":[]}},\"PropertyRuleCategory\":\"Data\",\"PropertyDisplayName\":\"Printing\"},{\"Name\":\"ContentLanguage\",\"InvariantType\":{\"Version\":\"1.345\",\"Type\":{\"Name\":\"Root\",\"Kind\":\"String\",\"EnumString\":\"\",\"Type\":[]}},\"PropertyRuleCategory\":\"Data\",\"PropertyDisplayName\":\"Content language\"}]}}]}}"
    },
    {
      "Category": 0,
      "DisplayName": "iconColor",
      "Hidden": false,
      "Name": "iconColor",
      "PropertyDataTypeKey": "String",
      "Tooltip": "A custom property",
      "Type": "{\"Version\":\"1.345\",\"Type\":{\"Name\":\"Root\",\"Kind\":\"String\",\"EnumString\":\"\",\"Type\":[]}}"
    },
    {
      "Category": 0,
      "DisplayName": "logo",
      "Hidden": false,
      "Name": "logo",
      "PropertyDataTypeKey": "String",
      "Tooltip": "A custom property",
      "Type": "{\"Version\":\"1.345\",\"Type\":{\"Name\":\"Root\",\"Kind\":\"String\",\"EnumString\":\"\",\"Type\":[]}}"
    },
    {
      "Category": 0,
      "DisplayName": "currentScreen",
      "Hidden": false,
      "Name": "currentScreen",
      "PropertyDataTypeKey": "String",
      "Tooltip": "A custom property",
      "Type": "{\"Version\":\"1.345\",\"Type\":{\"Name\":\"Root\",\"Kind\":\"String\",\"EnumString\":\"\",\"Type\":[]}}"
    },
    {
      "Category": 0,
      "DisplayName": "iconColorCurrent",
      "Hidden": false,
      "Name": "iconColorCurrent",
      "PropertyDataTypeKey": "String",
      "Tooltip": "A custom property",
      "Type": "{\"Version\":\"1.345\",\"Type\":{\"Name\":\"Root\",\"Kind\":\"String\",\"EnumString\":\"\",\"Type\":[]}}"
    }
  ],
  "FirstParty": true,
  "Id": "http://microsoft.com/appmagic/Component",
  "IsComponentLocked": false,
  "IsComponentTemplate": true,
  "IsCustomGroupControlTemplate": false,
  "IsPcfControl": false,
  "IsPremiumPcfControl": false,
  "IsWidgetTemplate": false,
  "LastModifiedTimestamp": "638762695597747879",
  "Name": "b6e286b74ab5404c9b80877af1a44005",
  "OverridableProperties": {},
  "TemplateOriginalName": "component",
  "Version": "1.0"
}