{
  "ControlStates": {
    "author_name1": {
      "AllowAccessToGlobals": true,
      "ControlPropertyState": [
        "FieldName",
        "Order",
        "FieldVariantName",
        "FieldDisplayName",
        "FieldType",
        "X",
        "Y",
        "Width",
        "Height",
        "ZIndex"
      ],
      "HasDynamicProperties": false,
      "IsAutoGenerated": false,
      "IsComponentDefinition": false,
      "IsDataControl": false,
      "IsFromScreenLayout": false,
      "IsGroupControl": false,
      "IsLocked": true,
      "LayoutName": "",
      "MetaDataIDKey": "",
      "Name": "author_name1",
      "ParentIndex": 1,
      "PersistMetaDataIDKey": false,
      "Properties": [
        {
          "Category": "Data",
          "PropertyName": "FieldName",
          "RuleProviderType": "Unknown"
        },
        {
          "Category": "Data",
          "PropertyName": "Order",
          "RuleProviderType": "Unknown"
        },
        {
          "Category": "Data",
          "PropertyName": "FieldVariantName",
          "RuleProviderType": "Unknown"
        },
        {
          "Category": "Data",
          "PropertyName": "FieldDisplayName",
          "RuleProviderType": "Unknown"
        },
        {
          "Category": "Data",
          "PropertyName": "FieldType",
          "RuleProviderType": "Unknown"
        },
        {
          "Category": "Design",
          "PropertyName": "X",
          "RuleProviderType": "Unknown"
        },
        {
          "Category": "Design",
          "PropertyName": "Y",
          "RuleProviderType": "Unknown"
        },
        {
          "Category": "Design",
          "PropertyName": "Width",
          "RuleProviderType": "Unknown"
        },
        {
          "Category": "Design",
          "PropertyName": "Height",
          "RuleProviderType": "Unknown"
        },
        {
          "Category": "Design",
          "PropertyName": "ZIndex",
          "RuleProviderType": "Unknown"
        }
      ],
      "StyleName": "",
      "Type": "ControlInfo"
    },
    "cbArticles": {
      "AllowAccessToGlobals": true,
      "ControlPropertyState": [
        "X",
        "Y",
        "Width",
        "Height",
        "DisplayMode",
        "ZIndex",
        {
          "AFDDataSourceName": "",
          "AutoRuleBindingEnabled": false,
          "AutoRuleBindingString": "",
          "InvariantPropertyName": "Items",
          "IsLockable": false,
          "NameMapSourceSchema": "?"
        },
        {
          "AFDDataSourceName": "",
          "AutoRuleBindingEnabled": false,
          "AutoRuleBindingString": "false",
          "InvariantPropertyName": "OnSelect",
          "IsLockable": false,
          "NameMapSourceSchema": "?"
        },
        {
          "AFDDataSourceName": "",
          "AutoRuleBindingEnabled": false,
          "AutoRuleBindingString": "true",
          "InvariantPropertyName": "Visible",
          "IsLockable": false,
          "NameMapSourceSchema": "?"
        }
      ],
      "HasDynamicProperties": false,
      "IsAutoGenerated": false,
      "IsComponentDefinition": false,
      "IsDataControl": false,
      "IsFromScreenLayout": false,
      "IsGroupControl": false,
      "IsLocked": false,
      "LayoutName": "",
      "MetaDataIDKey": "",
      "Name": "cbArticles",
      "ParentIndex": 3,
      "PersistMetaDataIDKey": false,
      "Properties": [
        {
          "Category": "Data",
          "PropertyName": "Items",
          "RuleProviderType": "Unknown"
        },
        {
          "Category": "Design",
          "PropertyName": "ZIndex",
          "RuleProviderType": "Unknown"
        },
        {
          "Category": "Design",
          "PropertyName": "DisplayMode",
          "RuleProviderType": "Unknown"
        },
        {
          "Category": "Design",
          "PropertyName": "Height",
          "RuleProviderType": "Unknown"
        },
        {
          "Category": "Design",
          "PropertyName": "Width",
          "RuleProviderType": "Unknown"
        },
        {
          "Category": "Design",
          "PropertyName": "Y",
          "RuleProviderType": "Unknown"
        },
        {
          "Category": "Design",
          "PropertyName": "X",
          "RuleProviderType": "Unknown"
        },
        {
          "Category": "Design",
          "PropertyName": "Visible",
          "RuleProviderType": "Unknown"
        },
        {
          "Category": "Behavior",
          "PropertyName": "OnSelect",
          "RuleProviderType": "Unknown"
        }
      ],
      "StyleName": "",
      "Type": "ControlInfo"
    },
    "comments_count1": {
      "AllowAccessToGlobals": true,
      "ControlPropertyState": [
        "FieldName",
        "Order",
        "FieldVariantName",
        "FieldDisplayName",
        "FieldType",
        "X",
        "Y",
        "Width",
        "Height",
        "ZIndex"
      ],
      "HasDynamicProperties": false,
      "IsAutoGenerated": false,
      "IsComponentDefinition": false,
      "IsDataControl": false,
      "IsFromScreenLayout": false,
      "IsGroupControl": false,
      "IsLocked": true,
      "LayoutName": "",
      "MetaDataIDKey": "",
      "Name": "comments_count1",
      "ParentIndex": 4,
      "PersistMetaDataIDKey": false,
      "Properties": [
        {
          "Category": "Data",
          "PropertyName": "FieldName",
          "RuleProviderType": "Unknown"
        },
        {
          "Category": "Data",
          "PropertyName": "Order",
          "RuleProviderType": "Unknown"
        },
        {
          "Category": "Data",
          "PropertyName": "FieldVariantName",
          "RuleProviderType": "Unknown"
        },
        {
          "Category": "Data",
          "PropertyName": "FieldDisplayName",
          "RuleProviderType": "Unknown"
        },
        {
          "Category": "Data",
          "PropertyName": "FieldType",
          "RuleProviderType": "Unknown"
        },
        {
          "Category": "Design",
          "PropertyName": "X",
          "RuleProviderType": "Unknown"
        },
        {
          "Category": "Design",
          "PropertyName": "Y",
          "RuleProviderType": "Unknown"
        },
        {
          "Category": "Design",
          "PropertyName": "Width",
          "RuleProviderType": "Unknown"
        },
        {
          "Category": "Design",
          "PropertyName": "Height",
          "RuleProviderType": "Unknown"
        },
        {
          "Category": "Design",
          "PropertyName": "ZIndex",
          "RuleProviderType": "Unknown"
        }
      ],
      "StyleName": "",
      "Type": "ControlInfo"
    },
    "detailListArticles": {
      "AllowAccessToGlobals": true,
      "ControlPropertyState": [
        {
          "AFDDataSourceName": "",
          "AutoRuleBindingEnabled": false,
          "AutoRuleBindingString": "",
          "InvariantPropertyName": "X",
          "IsLockable": false,
          "NameMapSourceSchema": "?"
        },
        {
          "AFDDataSourceName": "",
          "AutoRuleBindingEnabled": false,
          "AutoRuleBindingString": "",
          "InvariantPropertyName": "Y",
          "IsLockable": false,
          "NameMapSourceSchema": "?"
        },
        {
          "AFDDataSourceName": "",
          "AutoRuleBindingEnabled": false,
          "AutoRuleBindingString": "200",
          "InvariantPropertyName": "Width",
          "IsLockable": false,
          "NameMapSourceSchema": "?"
        },
        {
          "AFDDataSourceName": "",
          "AutoRuleBindingEnabled": false,
          "AutoRuleBindingString": "200",
          "InvariantPropertyName": "Height",
          "IsLockable": false,
          "NameMapSourceSchema": "?"
        },
        "DisplayMode",
        "ZIndex",
        {
          "AFDDataSourceName": "",
          "AutoRuleBindingEnabled": false,
          "AutoRuleBindingString": "",
          "InvariantPropertyName": "Items",
          "IsLockable": false,
          "NameMapSourceSchema": "?"
        },
        {
          "AFDDataSourceName": "",
          "AutoRuleBindingEnabled": false,
          "AutoRuleBindingString": "false",
          "InvariantPropertyName": "OnChange",
          "IsLockable": false,
          "NameMapSourceSchema": "?"
        },
        {
          "AFDDataSourceName": "",
          "AutoRuleBindingEnabled": false,
          "AutoRuleBindingString": "",
          "InvariantPropertyName": "columns_Items",
          "IsLockable": false,
          "NameMapSourceSchema": "?"
        },
        {
          "AFDDataSourceName": "",
          "AutoRuleBindingEnabled": false,
          "AutoRuleBindingString": "",
          "InvariantPropertyName": "SelectionType",
          "IsLockable": false,
          "NameMapSourceSchema": "?"
        },
        "OnSelect",
        {
          "AFDDataSourceName": "",
          "AutoRuleBindingEnabled": false,
          "AutoRuleBindingString": "",
          "InvariantPropertyName": "SelectRowsOnFocus",
          "IsLockable": false,
          "NameMapSourceSchema": "?"
        }
      ],
      "HasDynamicProperties": false,
      "IsAutoGenerated": false,
      "IsComponentDefinition": false,
      "IsDataControl": false,
      "IsFromScreenLayout": false,
      "IsGroupControl": false,
      "IsLocked": false,
      "LayoutName": "",
      "MetaDataIDKey": "",
      "Name": "detailListArticles",
      "ParentIndex": 4,
      "PersistMetaDataIDKey": false,
      "Properties": [
        {
          "Category": "Data",
          "PropertyName": "Items",
          "RuleProviderType": "Unknown"
        },
        {
          "Category": "Data",
          "PropertyName": "columns_Items",
          "RuleProviderType": "Unknown"
        },
        {
          "Category": "Data",
          "PropertyName": "SelectionType",
          "RuleProviderType": "Unknown"
        },
        {
          "Category": "Data",
          "PropertyName": "SelectRowsOnFocus",
          "RuleProviderType": "Unknown"
        },
        {
          "Category": "Design",
          "PropertyName": "DisplayMode",
          "RuleProviderType": "Unknown"
        },
        {
          "Category": "Design",
          "PropertyName": "Y",
          "RuleProviderType": "Unknown"
        },
        {
          "Category": "Design",
          "PropertyName": "X",
          "RuleProviderType": "Unknown"
        },
        {
          "Category": "Design",
          "PropertyName": "Width",
          "RuleProviderType": "Unknown"
        },
        {
          "Category": "Design",
          "PropertyName": "Height",
          "RuleProviderType": "Unknown"
        },
        {
          "Category": "Design",
          "PropertyName": "ZIndex",
          "RuleProviderType": "Unknown"
        },
        {
          "Category": "Behavior",
          "PropertyName": "OnChange",
          "RuleProviderType": "Unknown"
        },
        {
          "Category": "Behavior",
          "PropertyName": "OnSelect",
          "RuleProviderType": "Unknown"
        }
      ],
      "StyleName": "",
      "Type": "ControlInfo"
    },
    "formatted_date1": {
      "AllowAccessToGlobals": true,
      "ControlPropertyState": [
        "FieldName",
        "Order",
        "FieldVariantName",
        "FieldDisplayName",
        "FieldType",
        "X",
        "Y",
        "Width",
        "Height",
        "ZIndex"
      ],
      "HasDynamicProperties": false,
      "IsAutoGenerated": false,
      "IsComponentDefinition": false,
      "IsDataControl": false,
      "IsFromScreenLayout": false,
      "IsGroupControl": false,
      "IsLocked": true,
      "LayoutName": "",
      "MetaDataIDKey": "",
      "Name": "formatted_date1",
      "ParentIndex": 3,
      "PersistMetaDataIDKey": false,
      "Properties": [
        {
          "Category": "Data",
          "PropertyName": "FieldName",
          "RuleProviderType": "Unknown"
        },
        {
          "Category": "Data",
          "PropertyName": "Order",
          "RuleProviderType": "Unknown"
        },
        {
          "Category": "Data",
          "PropertyName": "FieldVariantName",
          "RuleProviderType": "Unknown"
        },
        {
          "Category": "Data",
          "PropertyName": "FieldDisplayName",
          "RuleProviderType": "Unknown"
        },
        {
          "Category": "Data",
          "PropertyName": "FieldType",
          "RuleProviderType": "Unknown"
        },
        {
          "Category": "Design",
          "PropertyName": "X",
          "RuleProviderType": "Unknown"
        },
        {
          "Category": "Design",
          "PropertyName": "Y",
          "RuleProviderType": "Unknown"
        },
        {
          "Category": "Design",
          "PropertyName": "Width",
          "RuleProviderType": "Unknown"
        },
        {
          "Category": "Design",
          "PropertyName": "Height",
          "RuleProviderType": "Unknown"
        },
        {
          "Category": "Design",
          "PropertyName": "ZIndex",
          "RuleProviderType": "Unknown"
        }
      ],
      "StyleName": "",
      "Type": "ControlInfo"
    },
    "Home Screen": {
      "AllowAccessToGlobals": true,
      "ControlPropertyState": [
        "Fill",
        "ImagePosition",
        "Height",
        "Width",
        "Size",
        "Orientation",
        "LoadingSpinner",
        "LoadingSpinnerColor"
      ],
      "IsAutoGenerated": false,
      "IsComponentDefinition": false,
      "IsDataControl": false,
      "IsFromScreenLayout": false,
      "IsGroupControl": false,
      "IsLocked": false,
      "LayoutName": "",
      "MetaDataIDKey": "",
      "Name": "Home Screen",
      "ParentIndex": 0,
      "PersistMetaDataIDKey": false,
      "Properties": [
        {
          "Category": "Design",
          "PropertyName": "Width",
          "RuleProviderType": "Unknown"
        },
        {
          "Category": "Design",
          "PropertyName": "Height",
          "RuleProviderType": "Unknown"
        },
        {
          "Category": "Design",
          "PropertyName": "ImagePosition",
          "RuleProviderType": "Unknown"
        },
        {
          "Category": "Design",
          "PropertyName": "Fill",
          "RuleProviderType": "Unknown"
        },
        {
          "Category": "Design",
          "PropertyName": "LoadingSpinner",
          "RuleProviderType": "Unknown"
        },
        {
          "Category": "Design",
          "PropertyName": "LoadingSpinnerColor",
          "RuleProviderType": "Unknown"
        },
        {
          "Category": "Design",
          "PropertyName": "Size",
          "RuleProviderType": "Unknown"
        },
        {
          "Category": "Design",
          "PropertyName": "Orientation",
          "RuleProviderType": "Unknown"
        }
      ],
      "StyleName": "defaultScreenStyle",
      "Type": "ControlInfo"
    },
    "imgDevTo": {
      "AllowAccessToGlobals": true,
      "ControlPropertyState": [
        {
          "AFDDataSourceName": "",
          "AutoRuleBindingEnabled": false,
          "AutoRuleBindingString": "SampleImage",
          "InvariantPropertyName": "Image",
          "IsLockable": false,
          "NameMapSourceSchema": "?"
        },
        "ImagePosition",
        "ImageRotation",
        "X",
        "Y",
        "Width",
        "Height",
        "Fill",
        "DisabledFill",
        "PressedFill",
        "HoverFill",
        "BorderColor",
        "DisabledBorderColor",
        "PressedBorderColor",
        "HoverBorderColor",
        "FocusedBorderColor",
        "BorderStyle",
        "DisplayMode",
        "ZIndex",
        "RadiusTopLeft",
        "RadiusTopRight",
        "RadiusBottomLeft",
        "RadiusBottomRight",
        "BorderThickness",
        "FocusedBorderThickness",
        {
          "AFDDataSourceName": "",
          "AutoRuleBindingEnabled": false,
          "AutoRuleBindingString": "",
          "InvariantPropertyName": "PaddingTop",
          "IsLockable": false,
          "NameMapSourceSchema": "?"
        },
        {
          "AFDDataSourceName": "",
          "AutoRuleBindingEnabled": false,
          "AutoRuleBindingString": "",
          "InvariantPropertyName": "PaddingRight",
          "IsLockable": false,
          "NameMapSourceSchema": "?"
        },
        {
          "AFDDataSourceName": "",
          "AutoRuleBindingEnabled": false,
          "AutoRuleBindingString": "",
          "InvariantPropertyName": "PaddingBottom",
          "IsLockable": false,
          "NameMapSourceSchema": "?"
        },
        {
          "AFDDataSourceName": "",
          "AutoRuleBindingEnabled": false,
          "AutoRuleBindingString": "",
          "InvariantPropertyName": "PaddingLeft",
          "IsLockable": false,
          "NameMapSourceSchema": "?"
        }
      ],
      "HasDynamicProperties": false,
      "IsAutoGenerated": false,
      "IsComponentDefinition": false,
      "IsDataControl": false,
      "IsFromScreenLayout": false,
      "IsGroupControl": false,
      "IsLocked": false,
      "LayoutName": "",
      "MetaDataIDKey": "",
      "Name": "imgDevTo",
      "ParentIndex": 0,
      "PersistMetaDataIDKey": false,
      "Properties": [
        {
          "Category": "Data",
          "PropertyName": "Image",
          "RuleProviderType": "Unknown"
        },
        {
          "Category": "Design",
          "PropertyName": "BorderThickness",
          "RuleProviderType": "Unknown"
        },
        {
          "Category": "Design",
          "PropertyName": "RadiusBottomRight",
          "RuleProviderType": "Unknown"
        },
        {
          "Category": "Design",
          "PropertyName": "RadiusBottomLeft",
          "RuleProviderType": "Unknown"
        },
        {
          "Category": "Design",
          "PropertyName": "RadiusTopRight",
          "RuleProviderType": "Unknown"
        },
        {
          "Category": "Design",
          "PropertyName": "RadiusTopLeft",
          "RuleProviderType": "Unknown"
        },
        {
          "Category": "Design",
          "PropertyName": "ZIndex",
          "RuleProviderType": "Unknown"
        },
        {
          "Category": "Design",
          "PropertyName": "DisplayMode",
          "RuleProviderType": "Unknown"
        },
        {
          "Category": "Design",
          "PropertyName": "BorderStyle",
          "RuleProviderType": "Unknown"
        },
        {
          "Category": "Design",
          "PropertyName": "DisabledBorderColor",
          "RuleProviderType": "Unknown"
        },
        {
          "Category": "Design",
          "PropertyName": "PaddingLeft",
          "RuleProviderType": "Unknown"
        },
        {
          "Category": "Design",
          "PropertyName": "PaddingBottom",
          "RuleProviderType": "Unknown"
        },
        {
          "Category": "Design",
          "PropertyName": "BorderColor",
          "RuleProviderType": "Unknown"
        },
        {
          "Category": "Design",
          "PropertyName": "DisabledFill",
          "RuleProviderType": "Unknown"
        },
        {
          "Category": "Design",
          "PropertyName": "PaddingRight",
          "RuleProviderType": "Unknown"
        },
        {
          "Category": "Design",
          "PropertyName": "PaddingTop",
          "RuleProviderType": "Unknown"
        },
        {
          "Category": "Design",
          "PropertyName": "FocusedBorderThickness",
          "RuleProviderType": "Unknown"
        },
        {
          "Category": "Design",
          "PropertyName": "Fill",
          "RuleProviderType": "Unknown"
        },
        {
          "Category": "Design",
          "PropertyName": "Height",
          "RuleProviderType": "Unknown"
        },
        {
          "Category": "Design",
          "PropertyName": "Width",
          "RuleProviderType": "Unknown"
        },
        {
          "Category": "Design",
          "PropertyName": "Y",
          "RuleProviderType": "Unknown"
        },
        {
          "Category": "Design",
          "PropertyName": "X",
          "RuleProviderType": "Unknown"
        },
        {
          "Category": "Design",
          "PropertyName": "ImageRotation",
          "RuleProviderType": "Unknown"
        },
        {
          "Category": "Design",
          "PropertyName": "ImagePosition",
          "RuleProviderType": "Unknown"
        },
        {
          "Category": "Design",
          "PropertyName": "FocusedBorderColor",
          "RuleProviderType": "Unknown"
        },
        {
          "Category": "Design",
          "PropertyName": "HoverBorderColor",
          "RuleProviderType": "Unknown"
        },
        {
          "Category": "Design",
          "PropertyName": "PressedBorderColor",
          "RuleProviderType": "Unknown"
        },
        {
          "Category": "Design",
          "PropertyName": "HoverFill",
          "RuleProviderType": "Unknown"
        },
        {
          "Category": "Design",
          "PropertyName": "PressedFill",
          "RuleProviderType": "Unknown"
        }
      ],
      "StyleName": "defaultImageStyle",
      "Type": "ControlInfo"
    },
    "org_name1": {
      "AllowAccessToGlobals": true,
      "ControlPropertyState": [
        "FieldName",
        "Order",
        "FieldVariantName",
        "FieldDisplayName",
        "FieldType",
        "X",
        "Y",
        "Width",
        "Height",
        "ZIndex"
      ],
      "HasDynamicProperties": false,
      "IsAutoGenerated": false,
      "IsComponentDefinition": false,
      "IsDataControl": false,
      "IsFromScreenLayout": false,
      "IsGroupControl": false,
      "IsLocked": true,
      "LayoutName": "",
      "MetaDataIDKey": "",
      "Name": "org_name1",
      "ParentIndex": 2,
      "PersistMetaDataIDKey": false,
      "Properties": [
        {
          "Category": "Data",
          "PropertyName": "FieldName",
          "RuleProviderType": "Unknown"
        },
        {
          "Category": "Data",
          "PropertyName": "Order",
          "RuleProviderType": "Unknown"
        },
        {
          "Category": "Data",
          "PropertyName": "FieldVariantName",
          "RuleProviderType": "Unknown"
        },
        {
          "Category": "Data",
          "PropertyName": "FieldDisplayName",
          "RuleProviderType": "Unknown"
        },
        {
          "Category": "Data",
          "PropertyName": "FieldType",
          "RuleProviderType": "Unknown"
        },
        {
          "Category": "Design",
          "PropertyName": "X",
          "RuleProviderType": "Unknown"
        },
        {
          "Category": "Design",
          "PropertyName": "Y",
          "RuleProviderType": "Unknown"
        },
        {
          "Category": "Design",
          "PropertyName": "Width",
          "RuleProviderType": "Unknown"
        },
        {
          "Category": "Design",
          "PropertyName": "Height",
          "RuleProviderType": "Unknown"
        },
        {
          "Category": "Design",
          "PropertyName": "ZIndex",
          "RuleProviderType": "Unknown"
        }
      ],
      "StyleName": "",
      "Type": "ControlInfo"
    },
    "pivMenu": {
      "AllowAccessToGlobals": true,
      "ControlPropertyState": [
        "X",
        {
          "AFDDataSourceName": "",
          "AutoRuleBindingEnabled": false,
          "AutoRuleBindingString": "0",
          "InvariantPropertyName": "Y",
          "IsLockable": false,
          "NameMapSourceSchema": "?"
        },
        {
          "AFDDataSourceName": "",
          "AutoRuleBindingEnabled": false,
          "AutoRuleBindingString": "",
          "InvariantPropertyName": "Width",
          "IsLockable": false,
          "NameMapSourceSchema": "?"
        },
        {
          "AFDDataSourceName": "",
          "AutoRuleBindingEnabled": false,
          "AutoRuleBindingString": "",
          "InvariantPropertyName": "Height",
          "IsLockable": false,
          "NameMapSourceSchema": "?"
        },
        "DisplayMode",
        "ZIndex",
        {
          "AFDDataSourceName": "",
          "AutoRuleBindingEnabled": false,
          "AutoRuleBindingString": "",
          "InvariantPropertyName": "Items",
          "IsLockable": false,
          "NameMapSourceSchema": "?"
        },
        {
          "AFDDataSourceName": "",
          "AutoRuleBindingEnabled": false,
          "AutoRuleBindingString": "\"\"",
          "InvariantPropertyName": "SelectedKey",
          "IsLockable": false,
          "NameMapSourceSchema": "?"
        },
        {
          "AFDDataSourceName": "",
          "AutoRuleBindingEnabled": false,
          "AutoRuleBindingString": "false",
          "InvariantPropertyName": "OnSelect",
          "IsLockable": false,
          "NameMapSourceSchema": "?"
        },
        {
          "AFDDataSourceName": "",
          "AutoRuleBindingEnabled": false,
          "AutoRuleBindingString": "\"\"",
          "InvariantPropertyName": "Theme",
          "IsLockable": false,
          "NameMapSourceSchema": "?"
        }
      ],
      "HasDynamicProperties": false,
      "IsAutoGenerated": false,
      "IsComponentDefinition": false,
      "IsDataControl": false,
      "IsFromScreenLayout": false,
      "IsGroupControl": false,
      "IsLocked": false,
      "LayoutName": "",
      "MetaDataIDKey": "",
      "Name": "pivMenu",
      "ParentIndex": 1,
      "PersistMetaDataIDKey": false,
      "Properties": [
        {
          "Category": "Data",
          "PropertyName": "Theme",
          "RuleProviderType": "Unknown"
        },
        {
          "Category": "Data",
          "PropertyName": "Items",
          "RuleProviderType": "Unknown"
        },
        {
          "Category": "Data",
          "PropertyName": "SelectedKey",
          "RuleProviderType": "Unknown"
        },
        {
          "Category": "Design",
          "PropertyName": "DisplayMode",
          "RuleProviderType": "Unknown"
        },
        {
          "Category": "Design",
          "PropertyName": "Height",
          "RuleProviderType": "Unknown"
        },
        {
          "Category": "Design",
          "PropertyName": "Width",
          "RuleProviderType": "Unknown"
        },
        {
          "Category": "Design",
          "PropertyName": "ZIndex",
          "RuleProviderType": "Unknown"
        },
        {
          "Category": "Design",
          "PropertyName": "X",
          "RuleProviderType": "Unknown"
        },
        {
          "Category": "Design",
          "PropertyName": "Y",
          "RuleProviderType": "Unknown"
        },
        {
          "Category": "Behavior",
          "PropertyName": "OnSelect",
          "RuleProviderType": "Unknown"
        }
      ],
      "StyleName": "",
      "Type": "ControlInfo"
    },
    "public_reactions_count1": {
      "AllowAccessToGlobals": true,
      "ControlPropertyState": [
        "FieldName",
        "Order",
        "FieldVariantName",
        "FieldDisplayName",
        "FieldType",
        "X",
        "Y",
        "Width",
        "Height",
        "ZIndex"
      ],
      "HasDynamicProperties": false,
      "IsAutoGenerated": false,
      "IsComponentDefinition": false,
      "IsDataControl": false,
      "IsFromScreenLayout": false,
      "IsGroupControl": false,
      "IsLocked": true,
      "LayoutName": "",
      "MetaDataIDKey": "",
      "Name": "public_reactions_count1",
      "ParentIndex": 5,
      "PersistMetaDataIDKey": false,
      "Properties": [
        {
          "Category": "Data",
          "PropertyName": "FieldName",
          "RuleProviderType": "Unknown"
        },
        {
          "Category": "Data",
          "PropertyName": "Order",
          "RuleProviderType": "Unknown"
        },
        {
          "Category": "Data",
          "PropertyName": "FieldVariantName",
          "RuleProviderType": "Unknown"
        },
        {
          "Category": "Data",
          "PropertyName": "FieldDisplayName",
          "RuleProviderType": "Unknown"
        },
        {
          "Category": "Data",
          "PropertyName": "FieldType",
          "RuleProviderType": "Unknown"
        },
        {
          "Category": "Design",
          "PropertyName": "X",
          "RuleProviderType": "Unknown"
        },
        {
          "Category": "Design",
          "PropertyName": "Y",
          "RuleProviderType": "Unknown"
        },
        {
          "Category": "Design",
          "PropertyName": "Width",
          "RuleProviderType": "Unknown"
        },
        {
          "Category": "Design",
          "PropertyName": "Height",
          "RuleProviderType": "Unknown"
        },
        {
          "Category": "Design",
          "PropertyName": "ZIndex",
          "RuleProviderType": "Unknown"
        }
      ],
      "StyleName": "",
      "Type": "ControlInfo"
    },
    "searchBox": {
      "AllowAccessToGlobals": true,
      "ControlPropertyState": [
        {
          "AFDDataSourceName": "",
          "AutoRuleBindingEnabled": false,
          "AutoRuleBindingString": "",
          "InvariantPropertyName": "X",
          "IsLockable": false,
          "NameMapSourceSchema": "?"
        },
        {
          "AFDDataSourceName": "",
          "AutoRuleBindingEnabled": false,
          "AutoRuleBindingString": "",
          "InvariantPropertyName": "Y",
          "IsLockable": false,
          "NameMapSourceSchema": "?"
        },
        {
          "AFDDataSourceName": "",
          "AutoRuleBindingEnabled": false,
          "AutoRuleBindingString": "",
          "InvariantPropertyName": "Width",
          "IsLockable": false,
          "NameMapSourceSchema": "?"
        },
        {
          "AFDDataSourceName": "",
          "AutoRuleBindingEnabled": false,
          "AutoRuleBindingString": "",
          "InvariantPropertyName": "Height",
          "IsLockable": false,
          "NameMapSourceSchema": "?"
        },
        "DisplayMode",
        "ZIndex",
        {
          "AFDDataSourceName": "",
          "AutoRuleBindingEnabled": false,
          "AutoRuleBindingString": "\"\"",
          "InvariantPropertyName": "Theme",
          "IsLockable": false,
          "NameMapSourceSchema": "?"
        },
        {
          "AFDDataSourceName": "",
          "AutoRuleBindingEnabled": false,
          "AutoRuleBindingString": "",
          "InvariantPropertyName": "AccessibilityLabel",
          "IsLockable": false,
          "NameMapSourceSchema": "?"
        }
      ],
      "HasDynamicProperties": false,
      "IsAutoGenerated": false,
      "IsComponentDefinition": false,
      "IsDataControl": false,
      "IsFromScreenLayout": false,
      "IsGroupControl": false,
      "IsLocked": false,
      "LayoutName": "",
      "MetaDataIDKey": "",
      "Name": "searchBox",
      "ParentIndex": 2,
      "PersistMetaDataIDKey": false,
      "Properties": [
        {
          "Category": "Data",
          "PropertyName": "AccessibilityLabel",
          "RuleProviderType": "Unknown"
        },
        {
          "Category": "Data",
          "PropertyName": "Theme",
          "RuleProviderType": "Unknown"
        },
        {
          "Category": "Design",
          "PropertyName": "ZIndex",
          "RuleProviderType": "Unknown"
        },
        {
          "Category": "Design",
          "PropertyName": "DisplayMode",
          "RuleProviderType": "Unknown"
        },
        {
          "Category": "Design",
          "PropertyName": "Height",
          "RuleProviderType": "Unknown"
        },
        {
          "Category": "Design",
          "PropertyName": "Width",
          "RuleProviderType": "Unknown"
        },
        {
          "Category": "Design",
          "PropertyName": "Y",
          "RuleProviderType": "Unknown"
        },
        {
          "Category": "Design",
          "PropertyName": "X",
          "RuleProviderType": "Unknown"
        }
      ],
      "StyleName": "",
      "Type": "ControlInfo"
    },
    "tags1": {
      "AllowAccessToGlobals": true,
      "ControlPropertyState": [
        "FieldName",
        "Order",
        "FieldVariantName",
        "FieldDisplayName",
        "FieldType",
        "X",
        "Y",
        "Width",
        "Height",
        "ZIndex"
      ],
      "HasDynamicProperties": false,
      "IsAutoGenerated": false,
      "IsComponentDefinition": false,
      "IsDataControl": false,
      "IsFromScreenLayout": false,
      "IsGroupControl": false,
      "IsLocked": true,
      "LayoutName": "",
      "MetaDataIDKey": "",
      "Name": "tags1",
      "ParentIndex": 6,
      "PersistMetaDataIDKey": false,
      "Properties": [
        {
          "Category": "Data",
          "PropertyName": "FieldName",
          "RuleProviderType": "Unknown"
        },
        {
          "Category": "Data",
          "PropertyName": "Order",
          "RuleProviderType": "Unknown"
        },
        {
          "Category": "Data",
          "PropertyName": "FieldVariantName",
          "RuleProviderType": "Unknown"
        },
        {
          "Category": "Data",
          "PropertyName": "FieldDisplayName",
          "RuleProviderType": "Unknown"
        },
        {
          "Category": "Data",
          "PropertyName": "FieldType",
          "RuleProviderType": "Unknown"
        },
        {
          "Category": "Design",
          "PropertyName": "X",
          "RuleProviderType": "Unknown"
        },
        {
          "Category": "Design",
          "PropertyName": "Y",
          "RuleProviderType": "Unknown"
        },
        {
          "Category": "Design",
          "PropertyName": "Width",
          "RuleProviderType": "Unknown"
        },
        {
          "Category": "Design",
          "PropertyName": "Height",
          "RuleProviderType": "Unknown"
        },
        {
          "Category": "Design",
          "PropertyName": "ZIndex",
          "RuleProviderType": "Unknown"
        }
      ],
      "StyleName": "",
      "Type": "ControlInfo"
    },
    "title1": {
      "AllowAccessToGlobals": true,
      "ControlPropertyState": [
        "FieldName",
        "Order",
        "FieldVariantName",
        "FieldDisplayName",
        "FieldType",
        "X",
        "Y",
        "Width",
        "Height",
        "ZIndex"
      ],
      "HasDynamicProperties": false,
      "IsAutoGenerated": false,
      "IsComponentDefinition": false,
      "IsDataControl": false,
      "IsFromScreenLayout": false,
      "IsGroupControl": false,
      "IsLocked": true,
      "LayoutName": "",
      "MetaDataIDKey": "",
      "Name": "title1",
      "ParentIndex": 0,
      "PersistMetaDataIDKey": false,
      "Properties": [
        {
          "Category": "Data",
          "PropertyName": "FieldName",
          "RuleProviderType": "Unknown"
        },
        {
          "Category": "Data",
          "PropertyName": "Order",
          "RuleProviderType": "Unknown"
        },
        {
          "Category": "Data",
          "PropertyName": "FieldVariantName",
          "RuleProviderType": "Unknown"
        },
        {
          "Category": "Data",
          "PropertyName": "FieldDisplayName",
          "RuleProviderType": "Unknown"
        },
        {
          "Category": "Data",
          "PropertyName": "FieldType",
          "RuleProviderType": "Unknown"
        },
        {
          "Category": "Design",
          "PropertyName": "X",
          "RuleProviderType": "Unknown"
        },
        {
          "Category": "Design",
          "PropertyName": "Y",
          "RuleProviderType": "Unknown"
        },
        {
          "Category": "Design",
          "PropertyName": "Width",
          "RuleProviderType": "Unknown"
        },
        {
          "Category": "Design",
          "PropertyName": "Height",
          "RuleProviderType": "Unknown"
        },
        {
          "Category": "Design",
          "PropertyName": "ZIndex",
          "RuleProviderType": "Unknown"
        }
      ],
      "StyleName": "",
      "Type": "ControlInfo"
    }
  },
  "TopParentName": "Home Screen"
}