{
  "appinfo": {
    "CustomGroupControlTemplateName": "",
    "FirstParty": true,
    "Id": "http://microsoft.com/appmagic/appinfo",
    "IsComponentTemplate": false,
    "IsCustomGroupControlTemplate": false,
    "IsPcfControl": false,
    "IsPremiumPcfControl": false,
    "IsWidgetTemplate": false,
    "LastModifiedTimestamp": "0",
    "Name": "appinfo",
    "OverridableProperties": {},
    "Version": "1.0"
  },
  "Badge": {
    "CustomGroupControlTemplateName": "",
    "FirstParty": true,
    "Id": "http://microsoft.com/appmagic/powercontrol/PowerApps_CoreControls_BadgeCanvas",
    "IsComponentTemplate": false,
    "IsCustomGroupControlTemplate": false,
    "IsPcfControl": true,
    "IsPremiumPcfControl": false,
    "IsWidgetTemplate": false,
    "LastModifiedTimestamp": "0",
    "Name": "PowerApps_CoreControls_BadgeCanvas",
    "OverridableProperties": {},
    "TemplateDisplayName": "Badge",
    "Version": "0.0.8"
  },
  "Button": {
    "CustomGroupControlTemplateName": "",
    "FirstParty": true,
    "Id": "http://microsoft.com/appmagic/powercontrol/PowerApps_CoreControls_ButtonCanvas",
    "IsComponentTemplate": false,
    "IsCustomGroupControlTemplate": false,
    "IsPcfControl": true,
    "IsPremiumPcfControl": false,
    "IsWidgetTemplate": false,
    "LastModifiedTimestamp": "0",
    "Name": "PowerApps_CoreControls_ButtonCanvas",
    "OverridableProperties": {},
    "TemplateDisplayName": "Button",
    "Version": "0.0.19"
  },
  "Checkbox": {
    "CustomGroupControlTemplateName": "",
    "FirstParty": true,
    "Id": "http://microsoft.com/appmagic/powercontrol/PowerApps_CoreControls_CheckboxCanvas",
    "IsComponentTemplate": false,
    "IsCustomGroupControlTemplate": false,
    "IsPcfControl": true,
    "IsPremiumPcfControl": false,
    "IsWidgetTemplate": false,
    "LastModifiedTimestamp": "0",
    "Name": "PowerApps_CoreControls_CheckboxCanvas",
    "OverridableProperties": {},
    "TemplateDisplayName": "Checkbox",
    "Version": "0.0.14"
  },
  "Combobox": {
    "CustomGroupControlTemplateName": "",
    "FirstParty": true,
    "Id": "http://microsoft.com/appmagic/powercontrol/PowerApps_CoreControls_ComboboxCanvas",
    "IsComponentTemplate": false,
    "IsCustomGroupControlTemplate": false,
    "IsPcfControl": true,
    "IsPremiumPcfControl": false,
    "IsWidgetTemplate": false,
    "LastModifiedTimestamp": "0",
    "Name": "PowerApps_CoreControls_ComboboxCanvas",
    "OverridableProperties": {},
    "TemplateDisplayName": "Combobox",
    "Version": "0.0.17"
  },
  "Date picker": {
    "CustomGroupControlTemplateName": "",
    "FirstParty": true,
    "Id": "http://microsoft.com/appmagic/powercontrol/PowerApps_CoreControls_DatePickerCanvas",
    "IsComponentTemplate": false,
    "IsCustomGroupControlTemplate": false,
    "IsPcfControl": true,
    "IsPremiumPcfControl": false,
    "IsWidgetTemplate": false,
    "LastModifiedTimestamp": "0",
    "Name": "PowerApps_CoreControls_DatePickerCanvas",
    "OverridableProperties": {},
    "TemplateDisplayName": "Date picker",
    "Version": "0.0.8"
  },
  "Dropdown": {
    "CustomGroupControlTemplateName": "",
    "FirstParty": true,
    "Id": "http://microsoft.com/appmagic/powercontrol/PowerApps_CoreControls_DropdownCanvas",
    "IsComponentTemplate": false,
    "IsCustomGroupControlTemplate": false,
    "IsPcfControl": true,
    "IsPremiumPcfControl": false,
    "IsWidgetTemplate": false,
    "LastModifiedTimestamp": "0",
    "Name": "PowerApps_CoreControls_DropdownCanvas",
    "OverridableProperties": {},
    "TemplateDisplayName": "Dropdown",
    "Version": "0.0.21"
  },
  "form": {
    "CustomGroupControlTemplateName": "",
    "FirstParty": true,
    "Id": "http://microsoft.com/appmagic/form",
    "IsComponentTemplate": false,
    "IsCustomGroupControlTemplate": false,
    "IsPcfControl": false,
    "IsPremiumPcfControl": false,
    "IsWidgetTemplate": true,
    "LastModifiedTimestamp": "0",
    "Name": "form",
    "OverridableProperties": {},
    "Version": "2.4.0"
  },
  "groupContainer": {
    "CustomGroupControlTemplateName": "",
    "FirstParty": true,
    "Id": "http://microsoft.com/appmagic/groupContainer",
    "IsComponentTemplate": false,
    "IsCustomGroupControlTemplate": false,
    "IsPcfControl": false,
    "IsPremiumPcfControl": false,
    "IsWidgetTemplate": true,
    "LastModifiedTimestamp": "0",
    "Name": "groupContainer",
    "OverridableProperties": {},
    "Version": "1.3.0"
  },
  "Header": {
    "CustomGroupControlTemplateName": "",
    "FirstParty": true,
    "Id": "http://microsoft.com/appmagic/powercontrol/Header",
    "IsComponentTemplate": false,
    "IsCustomGroupControlTemplate": false,
    "IsPcfControl": true,
    "IsPremiumPcfControl": false,
    "IsWidgetTemplate": false,
    "LastModifiedTimestamp": "0",
    "Name": "Header",
    "OverridableProperties": {},
    "TemplateDisplayName": "Header",
    "Version": "0.0.19"
  },
  "Host": {
    "CustomGroupControlTemplateName": "",
    "FirstParty": true,
    "HostType": "Default",
    "Id": "http://microsoft.com/appmagic/hostcontrol",
    "IsComponentTemplate": false,
    "IsCustomGroupControlTemplate": false,
    "IsPcfControl": false,
    "IsPremiumPcfControl": false,
    "IsWidgetTemplate": false,
    "LastModifiedTimestamp": "0",
    "Name": "hostControl",
    "OverridableProperties": {},
    "Version": "1.6.0"
  },
  "Information button": {
    "CustomGroupControlTemplateName": "",
    "FirstParty": true,
    "Id": "http://microsoft.com/appmagic/powercontrol/PowerApps_CoreControls_InfoButtonCanvas",
    "IsComponentTemplate": false,
    "IsCustomGroupControlTemplate": false,
    "IsPcfControl": true,
    "IsPremiumPcfControl": false,
    "IsWidgetTemplate": false,
    "LastModifiedTimestamp": "0",
    "Name": "PowerApps_CoreControls_InfoButtonCanvas",
    "OverridableProperties": {},
    "TemplateDisplayName": "Information button",
    "Version": "0.0.16"
  },
  "Link": {
    "CustomGroupControlTemplateName": "",
    "FirstParty": true,
    "Id": "http://microsoft.com/appmagic/powercontrol/PowerApps_CoreControls_LinkCanvas",
    "IsComponentTemplate": false,
    "IsCustomGroupControlTemplate": false,
    "IsPcfControl": true,
    "IsPremiumPcfControl": false,
    "IsWidgetTemplate": false,
    "LastModifiedTimestamp": "0",
    "Name": "PowerApps_CoreControls_LinkCanvas",
    "OverridableProperties": {},
    "TemplateDisplayName": "Link",
    "Version": "0.0.15"
  },
  "pcfDataField": {
    "CustomGroupControlTemplateName": "",
    "FirstParty": true,
    "Id": "http://microsoft.com/appmagic/pcfDataField",
    "IsComponentTemplate": false,
    "IsCustomGroupControlTemplate": false,
    "IsPcfControl": false,
    "IsPremiumPcfControl": false,
    "IsWidgetTemplate": true,
    "LastModifiedTimestamp": "0",
    "Name": "pcfDataField",
    "OverridableProperties": {},
    "Version": "1.4.0"
  },
  "Progress Bar": {
    "CustomGroupControlTemplateName": "",
    "FirstParty": true,
    "Id": "http://microsoft.com/appmagic/powercontrol/PowerApps_CoreControls_Progress",
    "IsComponentTemplate": false,
    "IsCustomGroupControlTemplate": false,
    "IsPcfControl": true,
    "IsPremiumPcfControl": false,
    "IsWidgetTemplate": false,
    "LastModifiedTimestamp": "0",
    "Name": "PowerApps_CoreControls_Progress",
    "OverridableProperties": {},
    "TemplateDisplayName": "Progress Bar",
    "Version": "1.1.9"
  },
  "Radio": {
    "CustomGroupControlTemplateName": "",
    "FirstParty": true,
    "Id": "http://microsoft.com/appmagic/powercontrol/PowerApps_CoreControls_RadioGroupCanvas",
    "IsComponentTemplate": false,
    "IsCustomGroupControlTemplate": false,
    "IsPcfControl": true,
    "IsPremiumPcfControl": false,
    "IsWidgetTemplate": false,
    "LastModifiedTimestamp": "0",
    "Name": "PowerApps_CoreControls_RadioGroupCanvas",
    "OverridableProperties": {},
    "TemplateDisplayName": "Radio",
    "Version": "0.0.9"
  },
  "screen": {
    "CustomGroupControlTemplateName": "",
    "FirstParty": true,
    "Id": "http://microsoft.com/appmagic/screen",
    "IsComponentTemplate": false,
    "IsCustomGroupControlTemplate": false,
    "IsPcfControl": false,
    "IsPremiumPcfControl": false,
    "IsWidgetTemplate": false,
    "LastModifiedTimestamp": "0",
    "Name": "screen",
    "OverridableProperties": {},
    "Version": "1.0"
  },
  "Slider": {
    "CustomGroupControlTemplateName": "",
    "FirstParty": true,
    "Id": "http://microsoft.com/appmagic/powercontrol/PowerApps_CoreControls_Slider",
    "IsComponentTemplate": false,
    "IsCustomGroupControlTemplate": false,
    "IsPcfControl": true,
    "IsPremiumPcfControl": false,
    "IsWidgetTemplate": false,
    "LastModifiedTimestamp": "0",
    "Name": "PowerApps_CoreControls_Slider",
    "OverridableProperties": {},
    "TemplateDisplayName": "Slider",
    "Version": "1.0.10"
  },
  "Spinner": {
    "CustomGroupControlTemplateName": "",
    "FirstParty": true,
    "Id": "http://microsoft.com/appmagic/powercontrol/PowerApps_CoreControls_Spinner",
    "IsComponentTemplate": false,
    "IsCustomGroupControlTemplate": false,
    "IsPcfControl": true,
    "IsPremiumPcfControl": false,
    "IsWidgetTemplate": false,
    "LastModifiedTimestamp": "0",
    "Name": "PowerApps_CoreControls_Spinner",
    "OverridableProperties": {},
    "TemplateDisplayName": "Spinner",
    "Version": "1.0.19"
  },
  "Tab list": {
    "CustomGroupControlTemplateName": "",
    "FirstParty": true,
    "Id": "http://microsoft.com/appmagic/powercontrol/PowerApps_CoreControls_TabList",
    "IsComponentTemplate": false,
    "IsCustomGroupControlTemplate": false,
    "IsPcfControl": true,
    "IsPremiumPcfControl": false,
    "IsWidgetTemplate": false,
    "LastModifiedTimestamp": "0",
    "Name": "PowerApps_CoreControls_TabList",
    "OverridableProperties": {},
    "TemplateDisplayName": "Tab list",
    "Version": "2.2.1"
  },
  "Table (Dataverse only)": {
    "CustomGroupControlTemplateName": "",
    "FirstParty": true,
    "Id": "http://microsoft.com/appmagic/powercontrol/PowerAppsOneGrid",
    "IsComponentTemplate": false,
    "IsCustomGroupControlTemplate": false,
    "IsPcfControl": true,
    "IsPremiumPcfControl": false,
    "IsWidgetTemplate": false,
    "LastModifiedTimestamp": "0",
    "Name": "PowerAppsOneGrid",
    "OverridableProperties": {},
    "TemplateDisplayName": "Table (Dataverse only)",
    "Version": "1.0.89"
  },
  "Text": {
    "CustomGroupControlTemplateName": "",
    "FirstParty": true,
    "Id": "http://microsoft.com/appmagic/powercontrol/PowerApps_CoreControls_TextCanvas",
    "IsComponentTemplate": false,
    "IsCustomGroupControlTemplate": false,
    "IsPcfControl": true,
    "IsPremiumPcfControl": false,
    "IsWidgetTemplate": false,
    "LastModifiedTimestamp": "0",
    "Name": "PowerApps_CoreControls_TextCanvas",
    "OverridableProperties": {},
    "TemplateDisplayName": "Text",
    "Version": "0.0.16"
  },
  "Text input": {
    "CustomGroupControlTemplateName": "",
    "FirstParty": true,
    "Id": "http://microsoft.com/appmagic/powercontrol/PowerApps_CoreControls_TextInputCanvas",
    "IsComponentTemplate": false,
    "IsCustomGroupControlTemplate": false,
    "IsPcfControl": true,
    "IsPremiumPcfControl": false,
    "IsWidgetTemplate": false,
    "LastModifiedTimestamp": "0",
    "Name": "PowerApps_CoreControls_TextInputCanvas",
    "OverridableProperties": {},
    "TemplateDisplayName": "Text input",
    "Version": "0.0.17"
  },
  "timer": {
    "CustomGroupControlTemplateName": "",
    "FirstParty": true,
    "Id": "http://microsoft.com/appmagic/timer",
    "IsComponentTemplate": false,
    "IsCustomGroupControlTemplate": false,
    "IsPcfControl": false,
    "IsPremiumPcfControl": false,
    "IsWidgetTemplate": true,
    "LastModifiedTimestamp": "0",
    "Name": "timer",
    "OverridableProperties": {},
    "Version": "2.1.0"
  },
  "Toggle": {
    "CustomGroupControlTemplateName": "",
    "FirstParty": true,
    "Id": "http://microsoft.com/appmagic/powercontrol/PowerApps_CoreControls_Toggle",
    "IsComponentTemplate": false,
    "IsCustomGroupControlTemplate": false,
    "IsPcfControl": true,
    "IsPremiumPcfControl": false,
    "IsWidgetTemplate": false,
    "LastModifiedTimestamp": "0",
    "Name": "PowerApps_CoreControls_Toggle",
    "OverridableProperties": {},
    "TemplateDisplayName": "Toggle",
    "Version": "1.0.13"
  },
  "typedDataCard": {
    "CustomGroupControlTemplateName": "",
    "FirstParty": true,
    "Id": "http://microsoft.com/appmagic/card",
    "IsComponentTemplate": false,
    "IsCustomGroupControlTemplate": false,
    "IsPcfControl": false,
    "IsPremiumPcfControl": false,
    "IsWidgetTemplate": false,
    "LastModifiedTimestamp": "0",
    "Name": "typedDataCard",
    "OverridableProperties": {},
    "Version": "1.0.6"
  }
}