<?xml version="1.0" encoding="utf-8"?>
<CanvasApp xmlns:xsi="http://www.w3.org/2001/XMLSchema-instance">
  <Name>sa_sharingcontent_3a43b</Name>
  <AppVersion>2023-10-20T16:32:16Z</AppVersion>
  <Status>Ready</Status>
  <CreatedByClientVersion>3.23082.20.0</CreatedByClientVersion>
  <MinClientVersion>3.23082.20.0</MinClientVersion>
  <Tags>{"primaryDeviceWidth":"375","primaryDeviceHeight":"667","supportsPortrait":"true","supportsLandscape":"true","primaryFormFactor":"Tablet","showStatusBar":"false","publisherVersion":"3.23082.20","minimumRequiredApiVersion":"2.2.0","hasComponent":"false","hasUnlockedComponent":"false","isUnifiedRootApp":"false","sienaVersion":"20230829T170954Z-3.23082.20.0"}</Tags>
  <IsCdsUpgraded>0</IsCdsUpgraded>
  <GalleryItemId xsi:nil="true"></GalleryItemId>
  <BackgroundColor>RGBA(0,176,240,1)</BackgroundColor>
  <DisplayName>Sharing Content</DisplayName>
  <Description>bugs fixed</Description>
  <CommitMessage></CommitMessage>
  <Publisher></Publisher>
  <AuthorizationReferences>[]</AuthorizationReferences>
  <ConnectionReferences>{}</ConnectionReferences>
  <DatabaseReferences>{"default.cds":{"databaseDetails":{"referenceType":"Environmental","environmentName":"default.cds","overrideValues":{"status":"NotSpecified"}},"dataSources":{"Configurations":{"entitySetName":"sa_configurationses","logicalName":"sa_configurations"}}}}</DatabaseReferences>
  <CanConsumeAppPass>1</CanConsumeAppPass>
  <CanvasAppType>2</CanvasAppType>
  <BypassConsent>0</BypassConsent>
  <EmbeddedApp xsi:nil="true"></EmbeddedApp>
  <IntroducedVersion>1.0</IntroducedVersion>
  <CdsDependencies>{"cdsdependencies":[{"componenttype":1,"logicalname":"sa_configurations"}]}</CdsDependencies>
  <IsCustomizable>1</IsCustomizable>
  <BackgroundImageUri>/CanvasApps/sa_sharingcontent_3a43b_BackgroundImageUri</BackgroundImageUri>
  <DocumentUri>/CanvasApps/sa_sharingcontent_3a43b_DocumentUri.msapp</DocumentUri>
</CanvasApp>