<?xml version="1.0" encoding="utf-8"?>
<Connector xmlns:xsi="http://www.w3.org/2001/XMLSchema-instance">
  <connectorid>5c834463-f47d-4959-9c3a-fa07810814e3</connectorid>
  <description>REST API for football data including live scores, fixtures, and player stats.</description>
  <displayname>API-Football</displayname>
  <iconbrandcolor>#007ee5</iconbrandcolor>
  <name>ba_api-2dfootball</name>
  <connectortype>1</connectortype>
  <openapidefinition>/Connector/ba_api-2dfootball_openapidefinition.json</openapidefinition>
  <connectionparameters>/Connector/ba_api-2dfootball_connectionparameters.json</connectionparameters>
  <policytemplateinstances>/Connector/ba_api-2dfootball_policytemplateinstances.json</policytemplateinstances>
  <iconblob>/Connector/ba_api-2dfootball_iconblob.Png</iconblob>
</Connector>