<?xml version="1.0" encoding="utf-8"?>
<savedqueries xmlns:xsi="http://www.w3.org/2001/XMLSchema-instance">
  <savedquery>
    <IsCustomizable>1</IsCustomizable>
    <CanBeDeleted>1</CanBeDeleted>
    <isquickfindquery>0</isquickfindquery>
    <isprivate>0</isprivate>
    <isdefault>0</isdefault>
    <savedqueryid>{526fceec-8c19-ee11-8f6d-002248595bba}</savedqueryid>
    <layoutxml>
      <grid name="resultset" jump="wa_title" select="1" icon="1" preview="1">
        <row name="result" id="wa_productid">
          <cell name="wa_title" width="200" />
          <cell name="wa_startdate" width="100" />
          <cell name="wa_enddate" width="100" />
          <cell name="wa_description" width="109" />
        </row>
      </grid>
    </layoutxml>
    <querytype>0</querytype>
    <fetchxml>
      <fetch version="1.0" output-format="xml-platform" mapping="logical">
        <entity name="wa_product">
          <attribute name="wa_title" />
          <attribute name="wa_productid" />
          <attribute name="wa_startdate" />
          <attribute name="wa_enddate" />
          <attribute name="wa_description" />
        </entity>
      </fetch>
    </fetchxml>
    <IntroducedVersion>1.0.0.0</IntroducedVersion>
    <LocalizedNames>
      <LocalizedName description="Demo Product View" languagecode="1033" />
    </LocalizedNames>
  </savedquery>
</savedqueries>